{
    "id":  118,
    "name":  "Arroz",
    "order":  10,
    "layout":  1,
    "published":  true,
    "is_extended":  false,
    "categories":  [
                       {
                           "id":  441,
                           "name":  "Arroz",
                           "order":  10,
                           "layout":  2,
                           "published":  true,
                           "is_extended":  false,
                           "image":  null,
                           "subtitle":  null,
                           "products":  [
                                            {
                                                "id":  "5044",
                                                "slug":  "arroz-redondo-hacendado-paquete",
                                                "limit":  999,
                                                "badges":  {
                                                               "is_water":  false,
                                                               "requires_age_check":  false
                                                           },
                                                "status":  null,
                                                "packaging":  "Paquete",
                                                "published":  true,
                                                "share_url":  "https://tienda.mercadona.es/product/5044/arroz-redondo-hacendado-paquete",
                                                "thumbnail":  "https://prod-mercadona.imgix.net/images/0daf43fb5761b823ce83c985930c97c9.jpg?fit=crop\u0026h=300\u0026w=300",
                                                "categories":  [
                                                                   {
                                                                       "id":  13,
                                                                       "name":  "Arroz, legumbres y pasta",
                                                                       "level":  0,
                                                                       "order":  10
                                                                   }
                                                               ],
                                                "display_name":  "Arroz redondo Hacendado",
                                                "unavailable_from":  null,
                                                "price_instructions":  {
                                                                           "iva":  null,
                                                                           "is_new":  false,
                                                                           "is_pack":  false,
                                                                           "pack_size":  null,
                                                                           "unit_name":  null,
                                                                           "unit_size":  1.0,
                                                                           "bulk_price":  "1.20",
                                                                           "unit_price":  "1.20",
                                                                           "approx_size":  false,
                                                                           "size_format":  "kg",
                                                                           "total_units":  null,
                                                                           "unit_selector":  true,
                                                                           "bunch_selector":  false,
                                                                           "drained_weight":  null,
                                                                           "selling_method":  0,
                                                                           "tax_percentage":  "4.000",
                                                                           "price_decreased":  false,
                                                                           "reference_price":  "1.200",
                                                                           "min_bunch_amount":  1.0,
                                                                           "reference_format":  "kg",
                                                                           "previous_unit_price":  null,
                                                                           "increment_bunch_amount":  1.0
                                                                       },
                                                "unavailable_weekdays":  [

                                                                         ],
                                                "is_new_arrival":  false
                                            },
                                            {
                                                "id":  "5063",
                                                "slug":  "arroz-largo-hacendado-paquete",
                                                "limit":  999,
                                                "badges":  {
                                                               "is_water":  false,
                                                               "requires_age_check":  false
                                                           },
                                                "status":  null,
                                                "packaging":  "Paquete",
                                                "published":  true,
                                                "share_url":  "https://tienda.mercadona.es/product/5063/arroz-largo-hacendado-paquete",
                                                "thumbnail":  "https://prod-mercadona.imgix.net/images/801f924df0d429d82c0a136901dcb9b0.jpg?fit=crop\u0026h=300\u0026w=300",
                                                "categories":  [
                                                                   {
                                                                       "id":  13,
                                                                       "name":  "Arroz, legumbres y pasta",
                                                                       "level":  0,
                                                                       "order":  10
                                                                   }
                                                               ],
                                                "display_name":  "Arroz largo Hacendado",
                                                "unavailable_from":  null,
                                                "price_instructions":  {
                                                                           "iva":  null,
                                                                           "is_new":  false,
                                                                           "is_pack":  false,
                                                                           "pack_size":  null,
                                                                           "unit_name":  null,
                                                                           "unit_size":  1.0,
                                                                           "bulk_price":  "1.20",
                                                                           "unit_price":  "1.20",
                                                                           "approx_size":  false,
                                                                           "size_format":  "kg",
                                                                           "total_units":  null,
                                                                           "unit_selector":  true,
                                                                           "bunch_selector":  false,
                                                                           "drained_weight":  null,
                                                                           "selling_method":  0,
                                                                           "tax_percentage":  "4.000",
                                                                           "price_decreased":  false,
                                                                           "reference_price":  "1.200",
                                                                           "min_bunch_amount":  1.0,
                                                                           "reference_format":  "kg",
                                                                           "previous_unit_price":  "        1.25",
                                                                           "increment_bunch_amount":  1.0
                                                                       },
                                                "unavailable_weekdays":  [

                                                                         ],
                                                "is_new_arrival":  false
                                            },
                                            {
                                                "id":  "5000",
                                                "slug":  "arroz-redondo-fallera-paquete",
                                                "limit":  999,
                                                "badges":  {
                                                               "is_water":  false,
                                                               "requires_age_check":  false
                                                           },
                                                "status":  null,
                                                "packaging":  "Paquete",
                                                "published":  true,
                                                "share_url":  "https://tienda.mercadona.es/product/5000/arroz-redondo-fallera-paquete",
                                                "thumbnail":  "https://prod-mercadona.imgix.net/images/3d5a3a0f0c7a9b8e1a6503dbe5be466d.jpg?fit=crop\u0026h=300\u0026w=300",
                                                "categories":  [
                                                                   {
                                                                       "id":  13,
                                                                       "name":  "Arroz, legumbres y pasta",
                                                                       "level":  0,
                                                                       "order":  10
                                                                   }
                                                               ],
                                                "display_name":  "Arroz redondo La Fallera",
                                                "unavailable_from":  null,
                                                "price_instructions":  {
                                                                           "iva":  4,
                                                                           "is_new":  false,
                                                                           "is_pack":  false,
                                                                           "pack_size":  null,
                                                                           "unit_name":  null,
                                                                           "unit_size":  1.0,
                                                                           "bulk_price":  "1.69",
                                                                           "unit_price":  "1.69",
                                                                           "approx_size":  false,
                                                                           "size_format":  "kg",
                                                                           "total_units":  null,
                                                                           "unit_selector":  true,
                                                                           "bunch_selector":  false,
                                                                           "drained_weight":  null,
                                                                           "selling_method":  0,
                                                                           "tax_percentage":  "4.000",
                                                                           "price_decreased":  false,
                                                                           "reference_price":  "1.690",
                                                                           "min_bunch_amount":  1.0,
                                                                           "reference_format":  "kg",
                                                                           "previous_unit_price":  null,
                                                                           "increment_bunch_amount":  1.0
                                                                       },
                                                "unavailable_weekdays":  [

                                                                         ],
                                                "is_new_arrival":  false
                                            },
                                            {
                                                "id":  "22280",
                                                "slug":  "arroz-cocido-basmati-sabroz-brillante-pack-2",
                                                "limit":  999,
                                                "badges":  {
                                                               "is_water":  false,
                                                               "requires_age_check":  false
                                                           },
                                                "status":  null,
                                                "packaging":  "Pack-2",
                                                "published":  true,
                                                "share_url":  "https://tienda.mercadona.es/product/22280/arroz-cocido-basmati-sabroz-brillante-pack-2",
                                                "thumbnail":  "https://prod-mercadona.imgix.net/images/485f5e653b6655185c51eec9858703cb.jpg?fit=crop\u0026h=300\u0026w=300",
                                                "categories":  [
                                                                   {
                                                                       "id":  13,
                                                                       "name":  "Arroz, legumbres y pasta",
                                                                       "level":  0,
                                                                       "order":  10
                                                                   }
                                                               ],
                                                "display_name":  "Arroz cocido basmati Sabroz",
                                                "unavailable_from":  null,
                                                "price_instructions":  {
                                                                           "iva":  null,
                                                                           "is_new":  false,
                                                                           "is_pack":  true,
                                                                           "pack_size":  0.125,
                                                                           "unit_name":  "vasitos",
                                                                           "unit_size":  0.25,
                                                                           "bulk_price":  "4.40",
                                                                           "unit_price":  "1.10",
                                                                           "approx_size":  false,
                                                                           "size_format":  "kg",
                                                                           "total_units":  2,
                                                                           "unit_selector":  true,
                                                                           "bunch_selector":  false,
                                                                           "drained_weight":  null,
                                                                           "selling_method":  0,
                                                                           "tax_percentage":  "10.000",
                                                                           "price_decreased":  false,
                                                                           "reference_price":  "4.400",
                                                                           "min_bunch_amount":  1.0,
                                                                           "reference_format":  "kg",
                                                                           "previous_unit_price":  null,
                                                                           "increment_bunch_amount":  1.0
                                                                       },
                                                "unavailable_weekdays":  [

                                                                         ],
                                                "is_new_arrival":  false
                                            },
                                            {
                                                "id":  "22281",
                                                "slug":  "arroz-cocido-integral-sabroz-brillante-pack-2",
                                                "limit":  999,
                                                "badges":  {
                                                               "is_water":  false,
                                                               "requires_age_check":  false
                                                           },
                                                "status":  null,
                                                "packaging":  "Pack-2",
                                                "published":  true,
                                                "share_url":  "https://tienda.mercadona.es/product/22281/arroz-cocido-integral-sabroz-brillante-pack-2",
                                                "thumbnail":  "https://prod-mercadona.imgix.net/images/3c538ead2ed048792639ef28915cfaef.jpg?fit=crop\u0026h=300\u0026w=300",
                                                "categories":  [
                                                                   {
                                                                       "id":  13,
                                                                       "name":  "Arroz, legumbres y pasta",
                                                                       "level":  0,
                                                                       "order":  10
                                                                   }
                                                               ],
                                                "display_name":  "Arroz cocido integral Sabroz",
                                                "unavailable_from":  null,
                                                "price_instructions":  {
                                                                           "iva":  null,
                                                                           "is_new":  false,
                                                                           "is_pack":  true,
                                                                           "pack_size":  0.125,
                                                                           "unit_name":  "vasitos",
                                                                           "unit_size":  0.25,
                                                                           "bulk_price":  "4.20",
                                                                           "unit_price":  "1.05",
                                                                           "approx_size":  false,
                                                                           "size_format":  "kg",
                                                                           "total_units":  2,
                                                                           "unit_selector":  true,
                                                                           "bunch_selector":  false,
                                                                           "drained_weight":  null,
                                                                           "selling_method":  0,
                                                                           "tax_percentage":  "10.000",
                                                                           "price_decreased":  false,
                                                                           "reference_price":  "4.200",
                                                                           "min_bunch_amount":  1.0,
                                                                           "reference_format":  "kg",
                                                                           "previous_unit_price":  null,
                                                                           "increment_bunch_amount":  1.0
                                                                       },
                                                "unavailable_weekdays":  [

                                                                         ],
                                                "is_new_arrival":  false
                                            },
                                            {
                                                "id":  "52790",
                                                "slug":  "arroz-albufera-hacendado-paquete",
                                                "limit":  999,
                                                "badges":  {
                                                               "is_water":  false,
                                                               "requires_age_check":  false
                                                           },
                                                "status":  null,
                                                "packaging":  "Paquete",
                                                "published":  true,
                                                "share_url":  "https://tienda.mercadona.es/product/52790/arroz-albufera-hacendado-paquete",
                                                "thumbnail":  "https://prod-mercadona.imgix.net/images/6a35bea8548f6137ff812a1265bfa155.jpg?fit=crop\u0026h=300\u0026w=300",
                                                "categories":  [
                                                                   {
                                                                       "id":  13,
                                                                       "name":  "Arroz, legumbres y pasta",
                                                                       "level":  0,
                                                                       "order":  10
                                                                   }
                                                               ],
                                                "display_name":  "Arroz Albufera Hacendado",
                                                "unavailable_from":  null,
                                                "price_instructions":  {
                                                                           "iva":  null,
                                                                           "is_new":  false,
                                                                           "is_pack":  false,
                                                                           "pack_size":  null,
                                                                           "unit_name":  null,
                                                                           "unit_size":  1.0,
                                                                           "bulk_price":  "2.95",
                                                                           "unit_price":  "2.95",
                                                                           "approx_size":  false,
                                                                           "size_format":  "kg",
                                                                           "total_units":  null,
                                                                           "unit_selector":  true,
                                                                           "bunch_selector":  false,
                                                                           "drained_weight":  null,
                                                                           "selling_method":  0,
                                                                           "tax_percentage":  "4.000",
                                                                           "price_decreased":  false,
                                                                           "reference_price":  "2.950",
                                                                           "min_bunch_amount":  1.0,
                                                                           "reference_format":  "kg",
                                                                           "previous_unit_price":  null,
                                                                           "increment_bunch_amount":  1.0
                                                                       },
                                                "unavailable_weekdays":  [

                                                                         ],
                                                "is_new_arrival":  false
                                            },
                                            {
                                                "id":  "22278",
                                                "slug":  "quinoa-cocida-blanca-roja-sabroz-brillante-pack-2",
                                                "limit":  999,
                                                "badges":  {
                                                               "is_water":  false,
                                                               "requires_age_check":  false
                                                           },
                                                "status":  null,
                                                "packaging":  "Pack-2",
                                                "published":  true,
                                                "share_url":  "https://tienda.mercadona.es/product/22278/quinoa-cocida-blanca-roja-sabroz-brillante-pack-2",
                                                "thumbnail":  "https://prod-mercadona.imgix.net/images/cccf4ae8ce7152534fba1cd7c2689433.jpg?fit=crop\u0026h=300\u0026w=300",
                                                "categories":  [
                                                                   {
                                                                       "id":  13,
                                                                       "name":  "Arroz, legumbres y pasta",
                                                                       "level":  0,
                                                                       "order":  10
                                                                   }
                                                               ],
                                                "display_name":  "Quinoa cocida blanca y roja Sabroz",
                                                "unavailable_from":  null,
                                                "price_instructions":  {
                                                                           "iva":  null,
                                                                           "is_new":  false,
                                                                           "is_pack":  true,
                                                                           "pack_size":  0.125,
                                                                           "unit_name":  "vasitos",
                                                                           "unit_size":  0.25,
                                                                           "bulk_price":  "5.80",
                                                                           "unit_price":  "1.45",
                                                                           "approx_size":  false,
                                                                           "size_format":  "kg",
                                                                           "total_units":  2,
                                                                           "unit_selector":  true,
                                                                           "bunch_selector":  false,
                                                                           "drained_weight":  null,
                                                                           "selling_method":  0,
                                                                           "tax_percentage":  "10.000",
                                                                           "price_decreased":  false,
                                                                           "reference_price":  "5.800",
                                                                           "min_bunch_amount":  1.0,
                                                                           "reference_format":  "kg",
                                                                           "previous_unit_price":  null,
                                                                           "increment_bunch_amount":  1.0
                                                                       },
                                                "unavailable_weekdays":  [

                                                                         ],
                                                "is_new_arrival":  false
                                            },
                                            {
                                                "id":  "22279",
                                                "slug":  "arroz-cocido-redondo-sabroz-brillante-pack-2",
                                                "limit":  999,
                                                "badges":  {
                                                               "is_water":  false,
                                                               "requires_age_check":  false
                                                           },
                                                "status":  null,
                                                "packaging":  "Pack-2",
                                                "published":  true,
                                                "share_url":  "https://tienda.mercadona.es/product/22279/arroz-cocido-redondo-sabroz-brillante-pack-2",
                                                "thumbnail":  "https://prod-mercadona.imgix.net/images/b87d489084215ea73d35d6c2d465f39e.jpg?fit=crop\u0026h=300\u0026w=300",
                                                "categories":  [
                                                                   {
                                                                       "id":  13,
                                                                       "name":  "Arroz, legumbres y pasta",
                                                                       "level":  0,
                                                                       "order":  10
                                                                   }
                                                               ],
                                                "display_name":  "Arroz cocido redondo Sabroz",
                                                "unavailable_from":  null,
                                                "price_instructions":  {
                                                                           "iva":  null,
                                                                           "is_new":  false,
                                                                           "is_pack":  true,
                                                                           "pack_size":  0.125,
                                                                           "unit_name":  "vasitos",
                                                                           "unit_size":  0.25,
                                                                           "bulk_price":  "4.20",
                                                                           "unit_price":  "1.05",
                                                                           "approx_size":  false,
                                                                           "size_format":  "kg",
                                                                           "total_units":  2,
                                                                           "unit_selector":  true,
                                                                           "bunch_selector":  false,
                                                                           "drained_weight":  null,
                                                                           "selling_method":  0,
                                                                           "tax_percentage":  "10.000",
                                                                           "price_decreased":  false,
                                                                           "reference_price":  "4.200",
                                                                           "min_bunch_amount":  1.0,
                                                                           "reference_format":  "kg",
                                                                           "previous_unit_price":  null,
                                                                           "increment_bunch_amount":  1.0
                                                                       },
                                                "unavailable_weekdays":  [

                                                                         ],
                                                "is_new_arrival":  false
                                            },
                                            {
                                                "id":  "5042",
                                                "slug":  "arroz-redondo-j-sendra-hacendado-paquete",
                                                "limit":  999,
                                                "badges":  {
                                                               "is_water":  false,
                                                               "requires_age_check":  false
                                                           },
                                                "status":  null,
                                                "packaging":  "Paquete",
                                                "published":  true,
                                                "share_url":  "https://tienda.mercadona.es/product/5042/arroz-redondo-j-sendra-hacendado-paquete",
                                                "thumbnail":  "https://prod-mercadona.imgix.net/images/44a0df1169e9ebdceb061ebea08b4d42.jpg?fit=crop\u0026h=300\u0026w=300",
                                                "categories":  [
                                                                   {
                                                                       "id":  13,
                                                                       "name":  "Arroz, legumbres y pasta",
                                                                       "level":  0,
                                                                       "order":  10
                                                                   }
                                                               ],
                                                "display_name":  "Arroz redondo J Sendra Hacendado",
                                                "unavailable_from":  null,
                                                "price_instructions":  {
                                                                           "iva":  4,
                                                                           "is_new":  false,
                                                                           "is_pack":  false,
                                                                           "pack_size":  null,
                                                                           "unit_name":  null,
                                                                           "unit_size":  1.0,
                                                                           "bulk_price":  "1.60",
                                                                           "unit_price":  "1.60",
                                                                           "approx_size":  false,
                                                                           "size_format":  "kg",
                                                                           "total_units":  null,
                                                                           "unit_selector":  true,
                                                                           "bunch_selector":  false,
                                                                           "drained_weight":  null,
                                                                           "selling_method":  0,
                                                                           "tax_percentage":  "4.000",
                                                                           "price_decreased":  false,
                                                                           "reference_price":  "1.600",
                                                                           "min_bunch_amount":  1.0,
                                                                           "reference_format":  "kg",
                                                                           "previous_unit_price":  null,
                                                                           "increment_bunch_amount":  1.0
                                                                       },
                                                "unavailable_weekdays":  [

                                                                         ],
                                                "is_new_arrival":  false
                                            },
                                            {
                                                "id":  "5002",
                                                "slug":  "arroz-basmati-aromatico-hacendado-paquete",
                                                "limit":  999,
                                                "badges":  {
                                                               "is_water":  false,
                                                               "requires_age_check":  false
                                                           },
                                                "status":  null,
                                                "packaging":  "Paquete",
                                                "published":  true,
                                                "share_url":  "https://tienda.mercadona.es/product/5002/arroz-basmati-aromatico-hacendado-paquete",
                                                "thumbnail":  "https://prod-mercadona.imgix.net/images/ff02e0b326c0d33682f76e66cc825dda.jpg?fit=crop\u0026h=300\u0026w=300",
                                                "categories":  [
                                                                   {
                                                                       "id":  13,
                                                                       "name":  "Arroz, legumbres y pasta",
                                                                       "level":  0,
                                                                       "order":  10
                                                                   }
                                                               ],
                                                "display_name":  "Arroz basmati aromático Hacendado",
                                                "unavailable_from":  null,
                                                "price_instructions":  {
                                                                           "iva":  null,
                                                                           "is_new":  false,
                                                                           "is_pack":  false,
                                                                           "pack_size":  null,
                                                                           "unit_name":  null,
                                                                           "unit_size":  1.0,
                                                                           "bulk_price":  "2.10",
                                                                           "unit_price":  "2.10",
                                                                           "approx_size":  false,
                                                                           "size_format":  "kg",
                                                                           "total_units":  null,
                                                                           "unit_selector":  true,
                                                                           "bunch_selector":  false,
                                                                           "drained_weight":  null,
                                                                           "selling_method":  0,
                                                                           "tax_percentage":  "4.000",
                                                                           "price_decreased":  false,
                                                                           "reference_price":  "2.100",
                                                                           "min_bunch_amount":  1.0,
                                                                           "reference_format":  "kg",
                                                                           "previous_unit_price":  null,
                                                                           "increment_bunch_amount":  1.0
                                                                       },
                                                "unavailable_weekdays":  [

                                                                         ],
                                                "is_new_arrival":  false
                                            },
                                            {
                                                "id":  "9395",
                                                "slug":  "cous-cous-mediano-bia-caja",
                                                "limit":  999,
                                                "badges":  {
                                                               "is_water":  false,
                                                               "requires_age_check":  false
                                                           },
                                                "status":  null,
                                                "packaging":  "Caja",
                                                "published":  true,
                                                "share_url":  "https://tienda.mercadona.es/product/9395/cous-cous-mediano-bia-caja",
                                                "thumbnail":  "https://prod-mercadona.imgix.net/images/ab155e76bb3242671ee34c6e11d4fd78.jpg?fit=crop\u0026h=300\u0026w=300",
                                                "categories":  [
                                                                   {
                                                                       "id":  13,
                                                                       "name":  "Arroz, legumbres y pasta",
                                                                       "level":  0,
                                                                       "order":  10
                                                                   }
                                                               ],
                                                "display_name":  "Cous cous mediano Hacendado",
                                                "unavailable_from":  null,
                                                "price_instructions":  {
                                                                           "iva":  null,
                                                                           "is_new":  false,
                                                                           "is_pack":  false,
                                                                           "pack_size":  null,
                                                                           "unit_name":  null,
                                                                           "unit_size":  1.0,
                                                                           "bulk_price":  "1.95",
                                                                           "unit_price":  "1.95",
                                                                           "approx_size":  false,
                                                                           "size_format":  "kg",
                                                                           "total_units":  null,
                                                                           "unit_selector":  true,
                                                                           "bunch_selector":  false,
                                                                           "drained_weight":  null,
                                                                           "selling_method":  0,
                                                                           "tax_percentage":  "10.000",
                                                                           "price_decreased":  false,
                                                                           "reference_price":  "1.950",
                                                                           "min_bunch_amount":  1.0,
                                                                           "reference_format":  "kg",
                                                                           "previous_unit_price":  null,
                                                                           "increment_bunch_amount":  1.0
                                                                       },
                                                "unavailable_weekdays":  [

                                                                         ],
                                                "is_new_arrival":  false
                                            },
                                            {
                                                "id":  "5020",
                                                "slug":  "arroz-vaporizado-hacendado-paquete",
                                                "limit":  999,
                                                "badges":  {
                                                               "is_water":  false,
                                                               "requires_age_check":  false
                                                           },
                                                "status":  null,
                                                "packaging":  "Paquete",
                                                "published":  true,
                                                "share_url":  "https://tienda.mercadona.es/product/5020/arroz-vaporizado-hacendado-paquete",
                                                "thumbnail":  "https://prod-mercadona.imgix.net/images/1c5a40f534247a5a8b8e16737c809be8.jpg?fit=crop\u0026h=300\u0026w=300",
                                                "categories":  [
                                                                   {
                                                                       "id":  13,
                                                                       "name":  "Arroz, legumbres y pasta",
                                                                       "level":  0,
                                                                       "order":  10
                                                                   }
                                                               ],
                                                "display_name":  "Arroz vaporizado Hacendado",
                                                "unavailable_from":  null,
                                                "price_instructions":  {
                                                                           "iva":  null,
                                                                           "is_new":  false,
                                                                           "is_pack":  false,
                                                                           "pack_size":  null,
                                                                           "unit_name":  null,
                                                                           "unit_size":  1.0,
                                                                           "bulk_price":  "1.55",
                                                                           "unit_price":  "1.55",
                                                                           "approx_size":  false,
                                                                           "size_format":  "kg",
                                                                           "total_units":  null,
                                                                           "unit_selector":  true,
                                                                           "bunch_selector":  false,
                                                                           "drained_weight":  null,
                                                                           "selling_method":  0,
                                                                           "tax_percentage":  "4.000",
                                                                           "price_decreased":  false,
                                                                           "reference_price":  "1.550",
                                                                           "min_bunch_amount":  1.0,
                                                                           "reference_format":  "kg",
                                                                           "previous_unit_price":  null,
                                                                           "increment_bunch_amount":  1.0
                                                                       },
                                                "unavailable_weekdays":  [

                                                                         ],
                                                "is_new_arrival":  false
                                            },
                                            {
                                                "id":  "9430",
                                                "slug":  "quinoa-hacendado-paquete",
                                                "limit":  999,
                                                "badges":  {
                                                               "is_water":  false,
                                                               "requires_age_check":  false
                                                           },
                                                "status":  null,
                                                "packaging":  "Paquete",
                                                "published":  true,
                                                "share_url":  "https://tienda.mercadona.es/product/9430/quinoa-hacendado-paquete",
                                                "thumbnail":  "https://prod-mercadona.imgix.net/images/5f96e6f16b3a5d30f2fd7135e3d1f74e.jpg?fit=crop\u0026h=300\u0026w=300",
                                                "categories":  [
                                                                   {
                                                                       "id":  13,
                                                                       "name":  "Arroz, legumbres y pasta",
                                                                       "level":  0,
                                                                       "order":  10
                                                                   }
                                                               ],
                                                "display_name":  "Quinoa Hacendado",
                                                "unavailable_from":  null,
                                                "price_instructions":  {
                                                                           "iva":  null,
                                                                           "is_new":  false,
                                                                           "is_pack":  false,
                                                                           "pack_size":  null,
                                                                           "unit_name":  null,
                                                                           "unit_size":  0.5,
                                                                           "bulk_price":  "5.40",
                                                                           "unit_price":  "2.70",
                                                                           "approx_size":  false,
                                                                           "size_format":  "kg",
                                                                           "total_units":  null,
                                                                           "unit_selector":  true,
                                                                           "bunch_selector":  false,
                                                                           "drained_weight":  null,
                                                                           "selling_method":  0,
                                                                           "tax_percentage":  "4.000",
                                                                           "price_decreased":  false,
                                                                           "reference_price":  "5.400",
                                                                           "min_bunch_amount":  1.0,
                                                                           "reference_format":  "kg",
                                                                           "previous_unit_price":  null,
                                                                           "increment_bunch_amount":  1.0
                                                                       },
                                                "unavailable_weekdays":  [

                                                                         ],
                                                "is_new_arrival":  false
                                            },
                                            {
                                                "id":  "5184",
                                                "slug":  "arroz-integral-largo-hacendado-paquete",
                                                "limit":  999,
                                                "badges":  {
                                                               "is_water":  false,
                                                               "requires_age_check":  false
                                                           },
                                                "status":  null,
                                                "packaging":  "Paquete",
                                                "published":  true,
                                                "share_url":  "https://tienda.mercadona.es/product/5184/arroz-integral-largo-hacendado-paquete",
                                                "thumbnail":  "https://prod-mercadona.imgix.net/images/4991480b2fe769d8673224a89d50636c.jpg?fit=crop\u0026h=300\u0026w=300",
                                                "categories":  [
                                                                   {
                                                                       "id":  13,
                                                                       "name":  "Arroz, legumbres y pasta",
                                                                       "level":  0,
                                                                       "order":  10
                                                                   }
                                                               ],
                                                "display_name":  "Arroz integral largo Hacendado",
                                                "unavailable_from":  null,
                                                "price_instructions":  {
                                                                           "iva":  4,
                                                                           "is_new":  false,
                                                                           "is_pack":  false,
                                                                           "pack_size":  null,
                                                                           "unit_name":  null,
                                                                           "unit_size":  1.0,
                                                                           "bulk_price":  "1.65",
                                                                           "unit_price":  "1.65",
                                                                           "approx_size":  false,
                                                                           "size_format":  "kg",
                                                                           "total_units":  null,
                                                                           "unit_selector":  true,
                                                                           "bunch_selector":  false,
                                                                           "drained_weight":  null,
                                                                           "selling_method":  0,
                                                                           "tax_percentage":  "4.000",
                                                                           "price_decreased":  false,
                                                                           "reference_price":  "1.650",
                                                                           "min_bunch_amount":  1.0,
                                                                           "reference_format":  "kg",
                                                                           "previous_unit_price":  null,
                                                                           "increment_bunch_amount":  1.0
                                                                       },
                                                "unavailable_weekdays":  [

                                                                         ],
                                                "is_new_arrival":  false
                                            },
                                            {
                                                "id":  "52637",
                                                "slug":  "arroz-redondo-sabor-cigala-paquete",
                                                "limit":  999,
                                                "badges":  {
                                                               "is_water":  false,
                                                               "requires_age_check":  false
                                                           },
                                                "status":  null,
                                                "packaging":  "Paquete",
                                                "published":  true,
                                                "share_url":  "https://tienda.mercadona.es/product/52637/arroz-redondo-sabor-cigala-paquete",
                                                "thumbnail":  "https://prod-mercadona.imgix.net/images/bc5fcc520250ffec2cada3273830046c.jpg?fit=crop\u0026h=300\u0026w=300",
                                                "categories":  [
                                                                   {
                                                                       "id":  13,
                                                                       "name":  "Arroz, legumbres y pasta",
                                                                       "level":  0,
                                                                       "order":  10
                                                                   }
                                                               ],
                                                "display_name":  "Arroz redondo Sabor",
                                                "unavailable_from":  null,
                                                "price_instructions":  {
                                                                           "iva":  4,
                                                                           "is_new":  false,
                                                                           "is_pack":  false,
                                                                           "pack_size":  null,
                                                                           "unit_name":  null,
                                                                           "unit_size":  1.0,
                                                                           "bulk_price":  "2.45",
                                                                           "unit_price":  "2.45",
                                                                           "approx_size":  false,
                                                                           "size_format":  "kg",
                                                                           "total_units":  null,
                                                                           "unit_selector":  true,
                                                                           "bunch_selector":  false,
                                                                           "drained_weight":  null,
                                                                           "selling_method":  0,
                                                                           "tax_percentage":  "4.000",
                                                                           "price_decreased":  false,
                                                                           "reference_price":  "2.450",
                                                                           "min_bunch_amount":  1.0,
                                                                           "reference_format":  "kg",
                                                                           "previous_unit_price":  null,
                                                                           "increment_bunch_amount":  1.0
                                                                       },
                                                "unavailable_weekdays":  [

                                                                         ],
                                                "is_new_arrival":  false
                                            },
                                            {
                                                "id":  "12972",
                                                "slug":  "arroz-largo-sabroz",
                                                "limit":  999,
                                                "badges":  {
                                                               "is_water":  false,
                                                               "requires_age_check":  false
                                                           },
                                                "status":  null,
                                                "packaging":  null,
                                                "published":  true,
                                                "share_url":  "https://tienda.mercadona.es/product/12972/arroz-largo-sabroz",
                                                "thumbnail":  "https://prod-mercadona.imgix.net/images/e2d8b845aff0cf75e5999abe2df136b7.jpg?fit=crop\u0026h=300\u0026w=300",
                                                "categories":  [
                                                                   {
                                                                       "id":  13,
                                                                       "name":  "Arroz, legumbres y pasta",
                                                                       "level":  0,
                                                                       "order":  10
                                                                   }
                                                               ],
                                                "display_name":  "Arroz largo Sabroz",
                                                "unavailable_from":  null,
                                                "price_instructions":  {
                                                                           "iva":  10,
                                                                           "is_new":  false,
                                                                           "is_pack":  true,
                                                                           "pack_size":  0.125,
                                                                           "unit_name":  "vasitos",
                                                                           "unit_size":  0.25,
                                                                           "bulk_price":  "4.40",
                                                                           "unit_price":  "1.10",
                                                                           "approx_size":  false,
                                                                           "size_format":  "kg",
                                                                           "total_units":  2,
                                                                           "unit_selector":  true,
                                                                           "bunch_selector":  false,
                                                                           "drained_weight":  null,
                                                                           "selling_method":  0,
                                                                           "tax_percentage":  "10.000",
                                                                           "price_decreased":  false,
                                                                           "reference_price":  "4.400",
                                                                           "min_bunch_amount":  1.0,
                                                                           "reference_format":  "kg",
                                                                           "previous_unit_price":  null,
                                                                           "increment_bunch_amount":  1.0
                                                                       },
                                                "unavailable_weekdays":  [

                                                                         ],
                                                "is_new_arrival":  false
                                            }
                                        ]
                       }
                   ],
    "next_category":  {
                          "id":  121,
                          "name":  "Legumbres"
                      }
}
