{
    "id":  233,
    "name":  "Limpiahogar y friegasuelos",
    "order":  374,
    "layout":  1,
    "published":  true,
    "is_extended":  false,
    "categories":  [
                       {
                           "id":  742,
                           "name":  "Friegasuelos",
                           "order":  374,
                           "layout":  2,
                           "published":  true,
                           "is_extended":  false,
                           "image":  null,
                           "subtitle":  null,
                           "products":  [
                                            {
                                                "id":  "24049",
                                                "slug":  "friegasuelos-cotton-bosque-verde-liquido-botella",
                                                "limit":  999,
                                                "badges":  {
                                                               "is_water":  false,
                                                               "requires_age_check":  false
                                                           },
                                                "status":  null,
                                                "packaging":  "Botella",
                                                "published":  true,
                                                "share_url":  "https://tienda.mercadona.es/product/24049/friegasuelos-cotton-bosque-verde-liquido-botella",
                                                "thumbnail":  "https://prod-mercadona.imgix.net/images/0c4e2834f38ae71bbd798cf0a67d8eb6.jpg?fit=crop\u0026h=300\u0026w=300",
                                                "categories":  [
                                                                   {
                                                                       "id":  26,
                                                                       "name":  "Limpieza y hogar",
                                                                       "level":  0,
                                                                       "order":  374
                                                                   }
                                                               ],
                                                "display_name":  "Friegasuelos Cotton Bosque Verde líquido",
                                                "unavailable_from":  null,
                                                "price_instructions":  {
                                                                           "iva":  null,
                                                                           "is_new":  false,
                                                                           "is_pack":  false,
                                                                           "pack_size":  null,
                                                                           "unit_name":  null,
                                                                           "unit_size":  1.5,
                                                                           "bulk_price":  "0.63",
                                                                           "unit_price":  "0.95",
                                                                           "approx_size":  false,
                                                                           "size_format":  "l",
                                                                           "total_units":  null,
                                                                           "unit_selector":  true,
                                                                           "bunch_selector":  false,
                                                                           "drained_weight":  null,
                                                                           "selling_method":  0,
                                                                           "tax_percentage":  "21.000",
                                                                           "price_decreased":  false,
                                                                           "reference_price":  "0.634",
                                                                           "min_bunch_amount":  1.0,
                                                                           "reference_format":  "L",
                                                                           "previous_unit_price":  null,
                                                                           "increment_bunch_amount":  1.0
                                                                       },
                                                "unavailable_weekdays":  [

                                                                         ],
                                                "is_new_arrival":  true
                                            },
                                            {
                                                "id":  "43347",
                                                "slug":  "friegasuelos-pino-bosque-verde-liquido-botella",
                                                "limit":  999,
                                                "badges":  {
                                                               "is_water":  false,
                                                               "requires_age_check":  false
                                                           },
                                                "status":  null,
                                                "packaging":  "Botella",
                                                "published":  true,
                                                "share_url":  "https://tienda.mercadona.es/product/43347/friegasuelos-pino-bosque-verde-liquido-botella",
                                                "thumbnail":  "https://prod-mercadona.imgix.net/images/ecbacb1a7fbbe9854e091dbd90addc27.jpg?fit=crop\u0026h=300\u0026w=300",
                                                "categories":  [
                                                                   {
                                                                       "id":  26,
                                                                       "name":  "Limpieza y hogar",
                                                                       "level":  0,
                                                                       "order":  374
                                                                   }
                                                               ],
                                                "display_name":  "Friegasuelos Pino Bosque Verde líquido",
                                                "unavailable_from":  null,
                                                "price_instructions":  {
                                                                           "iva":  21,
                                                                           "is_new":  false,
                                                                           "is_pack":  false,
                                                                           "pack_size":  null,
                                                                           "unit_name":  null,
                                                                           "unit_size":  1.5,
                                                                           "bulk_price":  "0.63",
                                                                           "unit_price":  "0.95",
                                                                           "approx_size":  false,
                                                                           "size_format":  "l",
                                                                           "total_units":  null,
                                                                           "unit_selector":  true,
                                                                           "bunch_selector":  false,
                                                                           "drained_weight":  null,
                                                                           "selling_method":  0,
                                                                           "tax_percentage":  "21.000",
                                                                           "price_decreased":  false,
                                                                           "reference_price":  "0.634",
                                                                           "min_bunch_amount":  1.0,
                                                                           "reference_format":  "L",
                                                                           "previous_unit_price":  null,
                                                                           "increment_bunch_amount":  1.0
                                                                       },
                                                "unavailable_weekdays":  [

                                                                         ],
                                                "is_new_arrival":  false
                                            },
                                            {
                                                "id":  "43320",
                                                "slug":  "friegasuelos-spa-bosque-verde-liquido-botella",
                                                "limit":  999,
                                                "badges":  {
                                                               "is_water":  false,
                                                               "requires_age_check":  false
                                                           },
                                                "status":  null,
                                                "packaging":  "Botella",
                                                "published":  true,
                                                "share_url":  "https://tienda.mercadona.es/product/43320/friegasuelos-spa-bosque-verde-liquido-botella",
                                                "thumbnail":  "https://prod-mercadona.imgix.net/images/710460cd3335f95111222c75d8d1a3d2.jpg?fit=crop\u0026h=300\u0026w=300",
                                                "categories":  [
                                                                   {
                                                                       "id":  26,
                                                                       "name":  "Limpieza y hogar",
                                                                       "level":  0,
                                                                       "order":  374
                                                                   }
                                                               ],
                                                "display_name":  "Friegasuelos Spa Bosque Verde líquido",
                                                "unavailable_from":  null,
                                                "price_instructions":  {
                                                                           "iva":  21,
                                                                           "is_new":  false,
                                                                           "is_pack":  false,
                                                                           "pack_size":  null,
                                                                           "unit_name":  null,
                                                                           "unit_size":  1.5,
                                                                           "bulk_price":  "0.63",
                                                                           "unit_price":  "0.95",
                                                                           "approx_size":  false,
                                                                           "size_format":  "l",
                                                                           "total_units":  null,
                                                                           "unit_selector":  true,
                                                                           "bunch_selector":  false,
                                                                           "drained_weight":  null,
                                                                           "selling_method":  0,
                                                                           "tax_percentage":  "21.000",
                                                                           "price_decreased":  false,
                                                                           "reference_price":  "0.634",
                                                                           "min_bunch_amount":  1.0,
                                                                           "reference_format":  "L",
                                                                           "previous_unit_price":  null,
                                                                           "increment_bunch_amount":  1.0
                                                                       },
                                                "unavailable_weekdays":  [

                                                                         ],
                                                "is_new_arrival":  false
                                            },
                                            {
                                                "id":  "44300",
                                                "slug":  "friegasuelos-classic-bosque-verde-concentrado-perfume-intenso-duradero-botella",
                                                "limit":  999,
                                                "badges":  {
                                                               "is_water":  false,
                                                               "requires_age_check":  false
                                                           },
                                                "status":  null,
                                                "packaging":  "Botella",
                                                "published":  true,
                                                "share_url":  "https://tienda.mercadona.es/product/44300/friegasuelos-classic-bosque-verde-concentrado-perfume-intenso-duradero-botella",
                                                "thumbnail":  "https://prod-mercadona.imgix.net/images/a587f976dec17de63bf8f5fc6619c9be.jpg?fit=crop\u0026h=300\u0026w=300",
                                                "categories":  [
                                                                   {
                                                                       "id":  26,
                                                                       "name":  "Limpieza y hogar",
                                                                       "level":  0,
                                                                       "order":  374
                                                                   }
                                                               ],
                                                "display_name":  "Friegasuelos Classic Bosque Verde concentrado",
                                                "unavailable_from":  null,
                                                "price_instructions":  {
                                                                           "iva":  null,
                                                                           "is_new":  false,
                                                                           "is_pack":  false,
                                                                           "pack_size":  null,
                                                                           "unit_name":  null,
                                                                           "unit_size":  1.0,
                                                                           "bulk_price":  "1.70",
                                                                           "unit_price":  "1.70",
                                                                           "approx_size":  false,
                                                                           "size_format":  "l",
                                                                           "total_units":  null,
                                                                           "unit_selector":  true,
                                                                           "bunch_selector":  false,
                                                                           "drained_weight":  null,
                                                                           "selling_method":  0,
                                                                           "tax_percentage":  "21.000",
                                                                           "price_decreased":  false,
                                                                           "reference_price":  "1.700",
                                                                           "min_bunch_amount":  1.0,
                                                                           "reference_format":  "L",
                                                                           "previous_unit_price":  null,
                                                                           "increment_bunch_amount":  1.0
                                                                       },
                                                "unavailable_weekdays":  [

                                                                         ],
                                                "is_new_arrival":  false
                                            },
                                            {
                                                "id":  "44301",
                                                "slug":  "friegasuelos-petalos-bosque-verde-concentrado-perfume-intenso-duradero-botella",
                                                "limit":  999,
                                                "badges":  {
                                                               "is_water":  false,
                                                               "requires_age_check":  false
                                                           },
                                                "status":  null,
                                                "packaging":  "Botella",
                                                "published":  true,
                                                "share_url":  "https://tienda.mercadona.es/product/44301/friegasuelos-petalos-bosque-verde-concentrado-perfume-intenso-duradero-botella",
                                                "thumbnail":  "https://prod-mercadona.imgix.net/images/cec5d5dd8a001a15bd4a166df4f6696a.jpg?fit=crop\u0026h=300\u0026w=300",
                                                "categories":  [
                                                                   {
                                                                       "id":  26,
                                                                       "name":  "Limpieza y hogar",
                                                                       "level":  0,
                                                                       "order":  374
                                                                   }
                                                               ],
                                                "display_name":  "Friegasuelos Pétalos Bosque Verde concentrado",
                                                "unavailable_from":  null,
                                                "price_instructions":  {
                                                                           "iva":  null,
                                                                           "is_new":  false,
                                                                           "is_pack":  false,
                                                                           "pack_size":  null,
                                                                           "unit_name":  null,
                                                                           "unit_size":  1.0,
                                                                           "bulk_price":  "1.70",
                                                                           "unit_price":  "1.70",
                                                                           "approx_size":  false,
                                                                           "size_format":  "l",
                                                                           "total_units":  null,
                                                                           "unit_selector":  true,
                                                                           "bunch_selector":  false,
                                                                           "drained_weight":  null,
                                                                           "selling_method":  0,
                                                                           "tax_percentage":  "21.000",
                                                                           "price_decreased":  false,
                                                                           "reference_price":  "1.700",
                                                                           "min_bunch_amount":  1.0,
                                                                           "reference_format":  "L",
                                                                           "previous_unit_price":  null,
                                                                           "increment_bunch_amount":  1.0
                                                                       },
                                                "unavailable_weekdays":  [

                                                                         ],
                                                "is_new_arrival":  false
                                            },
                                            {
                                                "id":  "7963",
                                                "slug":  "friegasuelos-floral-bosque-verde-liquido-botella",
                                                "limit":  999,
                                                "badges":  {
                                                               "is_water":  false,
                                                               "requires_age_check":  false
                                                           },
                                                "status":  null,
                                                "packaging":  "Botella",
                                                "published":  true,
                                                "share_url":  "https://tienda.mercadona.es/product/7963/friegasuelos-floral-bosque-verde-liquido-botella",
                                                "thumbnail":  "https://prod-mercadona.imgix.net/images/3cbb9d39e8c0d5bce5734249ee0b43bd.jpg?fit=crop\u0026h=300\u0026w=300",
                                                "categories":  [
                                                                   {
                                                                       "id":  26,
                                                                       "name":  "Limpieza y hogar",
                                                                       "level":  0,
                                                                       "order":  374
                                                                   }
                                                               ],
                                                "display_name":  "Friegasuelos Floral Bosque Verde líquido",
                                                "unavailable_from":  null,
                                                "price_instructions":  {
                                                                           "iva":  21,
                                                                           "is_new":  false,
                                                                           "is_pack":  false,
                                                                           "pack_size":  null,
                                                                           "unit_name":  null,
                                                                           "unit_size":  1.5,
                                                                           "bulk_price":  "0.63",
                                                                           "unit_price":  "0.95",
                                                                           "approx_size":  false,
                                                                           "size_format":  "l",
                                                                           "total_units":  null,
                                                                           "unit_selector":  true,
                                                                           "bunch_selector":  false,
                                                                           "drained_weight":  null,
                                                                           "selling_method":  0,
                                                                           "tax_percentage":  "21.000",
                                                                           "price_decreased":  false,
                                                                           "reference_price":  "0.634",
                                                                           "min_bunch_amount":  1.0,
                                                                           "reference_format":  "L",
                                                                           "previous_unit_price":  null,
                                                                           "increment_bunch_amount":  1.0
                                                                       },
                                                "unavailable_weekdays":  [

                                                                         ],
                                                "is_new_arrival":  false
                                            },
                                            {
                                                "id":  "43070",
                                                "slug":  "friegasuelos-insecticida-krisul-liquido-botella",
                                                "limit":  999,
                                                "badges":  {
                                                               "is_water":  false,
                                                               "requires_age_check":  false
                                                           },
                                                "status":  null,
                                                "packaging":  "Botella",
                                                "published":  true,
                                                "share_url":  "https://tienda.mercadona.es/product/43070/friegasuelos-insecticida-krisul-liquido-botella",
                                                "thumbnail":  "https://prod-mercadona.imgix.net/images/29bb3e58f87fe4671e364098c500a25f.jpg?fit=crop\u0026h=300\u0026w=300",
                                                "categories":  [
                                                                   {
                                                                       "id":  26,
                                                                       "name":  "Limpieza y hogar",
                                                                       "level":  0,
                                                                       "order":  374
                                                                   }
                                                               ],
                                                "display_name":  "Friegasuelos Insecticida Krisul líquido",
                                                "unavailable_from":  null,
                                                "price_instructions":  {
                                                                           "iva":  21,
                                                                           "is_new":  false,
                                                                           "is_pack":  false,
                                                                           "pack_size":  null,
                                                                           "unit_name":  null,
                                                                           "unit_size":  1.0,
                                                                           "bulk_price":  "2.35",
                                                                           "unit_price":  "2.35",
                                                                           "approx_size":  false,
                                                                           "size_format":  "l",
                                                                           "total_units":  null,
                                                                           "unit_selector":  true,
                                                                           "bunch_selector":  false,
                                                                           "drained_weight":  null,
                                                                           "selling_method":  0,
                                                                           "tax_percentage":  "21.000",
                                                                           "price_decreased":  false,
                                                                           "reference_price":  "2.350",
                                                                           "min_bunch_amount":  1.0,
                                                                           "reference_format":  "L",
                                                                           "previous_unit_price":  null,
                                                                           "increment_bunch_amount":  1.0
                                                                       },
                                                "unavailable_weekdays":  [

                                                                         ],
                                                "is_new_arrival":  false
                                            },
                                            {
                                                "id":  "71527",
                                                "slug":  "toallitas-limpiadoras-suelo-bosque-verde-paquete",
                                                "limit":  999,
                                                "badges":  {
                                                               "is_water":  false,
                                                               "requires_age_check":  false
                                                           },
                                                "status":  null,
                                                "packaging":  "Paquete",
                                                "published":  true,
                                                "share_url":  "https://tienda.mercadona.es/product/71527/toallitas-limpiadoras-suelo-bosque-verde-paquete",
                                                "thumbnail":  "https://prod-mercadona.imgix.net/images/5ae8ad22b809b0a866256fc40a94b416.jpg?fit=crop\u0026h=300\u0026w=300",
                                                "categories":  [
                                                                   {
                                                                       "id":  26,
                                                                       "name":  "Limpieza y hogar",
                                                                       "level":  0,
                                                                       "order":  374
                                                                   }
                                                               ],
                                                "display_name":  "Toallitas limpiadoras de suelo Bosque Verde",
                                                "unavailable_from":  null,
                                                "price_instructions":  {
                                                                           "iva":  21,
                                                                           "is_new":  false,
                                                                           "is_pack":  false,
                                                                           "pack_size":  null,
                                                                           "unit_name":  null,
                                                                           "unit_size":  20.0,
                                                                           "bulk_price":  "0.08",
                                                                           "unit_price":  "1.60",
                                                                           "approx_size":  false,
                                                                           "size_format":  "ud",
                                                                           "total_units":  null,
                                                                           "unit_selector":  true,
                                                                           "bunch_selector":  false,
                                                                           "drained_weight":  null,
                                                                           "selling_method":  0,
                                                                           "tax_percentage":  "21.000",
                                                                           "price_decreased":  false,
                                                                           "reference_price":  "0.080",
                                                                           "min_bunch_amount":  1.0,
                                                                           "reference_format":  "ud",
                                                                           "previous_unit_price":  null,
                                                                           "increment_bunch_amount":  1.0
                                                                       },
                                                "unavailable_weekdays":  [

                                                                         ],
                                                "is_new_arrival":  false
                                            },
                                            {
                                                "id":  "13995",
                                                "slug":  "cera-multisuperficies-bosque-verde-botella",
                                                "limit":  999,
                                                "badges":  {
                                                               "is_water":  false,
                                                               "requires_age_check":  false
                                                           },
                                                "status":  null,
                                                "packaging":  "Botella",
                                                "published":  true,
                                                "share_url":  "https://tienda.mercadona.es/product/13995/cera-multisuperficies-bosque-verde-botella",
                                                "thumbnail":  "https://prod-mercadona.imgix.net/images/8f1c22d3f032d0e2dbd58ff6b4f6fede.jpg?fit=crop\u0026h=300\u0026w=300",
                                                "categories":  [
                                                                   {
                                                                       "id":  26,
                                                                       "name":  "Limpieza y hogar",
                                                                       "level":  0,
                                                                       "order":  374
                                                                   }
                                                               ],
                                                "display_name":  "Cera Multisuperficies Bosque Verde",
                                                "unavailable_from":  null,
                                                "price_instructions":  {
                                                                           "iva":  21,
                                                                           "is_new":  false,
                                                                           "is_pack":  false,
                                                                           "pack_size":  null,
                                                                           "unit_name":  null,
                                                                           "unit_size":  1.0,
                                                                           "bulk_price":  "4.50",
                                                                           "unit_price":  "4.50",
                                                                           "approx_size":  false,
                                                                           "size_format":  "l",
                                                                           "total_units":  null,
                                                                           "unit_selector":  true,
                                                                           "bunch_selector":  false,
                                                                           "drained_weight":  null,
                                                                           "selling_method":  0,
                                                                           "tax_percentage":  "21.000",
                                                                           "price_decreased":  false,
                                                                           "reference_price":  "4.500",
                                                                           "min_bunch_amount":  1.0,
                                                                           "reference_format":  "L",
                                                                           "previous_unit_price":  null,
                                                                           "increment_bunch_amount":  1.0
                                                                       },
                                                "unavailable_weekdays":  [

                                                                         ],
                                                "is_new_arrival":  false
                                            },
                                            {
                                                "id":  "13994",
                                                "slug":  "abrillantador-suelos-bosque-verde-botella",
                                                "limit":  999,
                                                "badges":  {
                                                               "is_water":  false,
                                                               "requires_age_check":  false
                                                           },
                                                "status":  null,
                                                "packaging":  "Botella",
                                                "published":  true,
                                                "share_url":  "https://tienda.mercadona.es/product/13994/abrillantador-suelos-bosque-verde-botella",
                                                "thumbnail":  "https://prod-mercadona.imgix.net/images/8eb198c05bef247a59d5a14d39b8f835.jpg?fit=crop\u0026h=300\u0026w=300",
                                                "categories":  [
                                                                   {
                                                                       "id":  26,
                                                                       "name":  "Limpieza y hogar",
                                                                       "level":  0,
                                                                       "order":  374
                                                                   }
                                                               ],
                                                "display_name":  "Abrillantador suelos Bosque Verde",
                                                "unavailable_from":  null,
                                                "price_instructions":  {
                                                                           "iva":  21,
                                                                           "is_new":  false,
                                                                           "is_pack":  false,
                                                                           "pack_size":  null,
                                                                           "unit_name":  null,
                                                                           "unit_size":  1.0,
                                                                           "bulk_price":  "2.50",
                                                                           "unit_price":  "2.50",
                                                                           "approx_size":  false,
                                                                           "size_format":  "l",
                                                                           "total_units":  null,
                                                                           "unit_selector":  true,
                                                                           "bunch_selector":  false,
                                                                           "drained_weight":  null,
                                                                           "selling_method":  0,
                                                                           "tax_percentage":  "21.000",
                                                                           "price_decreased":  false,
                                                                           "reference_price":  "2.500",
                                                                           "min_bunch_amount":  1.0,
                                                                           "reference_format":  "L",
                                                                           "previous_unit_price":  null,
                                                                           "increment_bunch_amount":  1.0
                                                                       },
                                                "unavailable_weekdays":  [

                                                                         ],
                                                "is_new_arrival":  false
                                            }
                                        ]
                       },
                       {
                           "id":  743,
                           "name":  "Limpiahogar",
                           "order":  374,
                           "layout":  2,
                           "published":  true,
                           "is_extended":  false,
                           "image":  null,
                           "subtitle":  null,
                           "products":  [
                                            {
                                                "id":  "43315",
                                                "slug":  "limpiahogar-aloe-vera-bosque-verde-concentrado-botella",
                                                "limit":  999,
                                                "badges":  {
                                                               "is_water":  false,
                                                               "requires_age_check":  false
                                                           },
                                                "status":  null,
                                                "packaging":  "Botella",
                                                "published":  true,
                                                "share_url":  "https://tienda.mercadona.es/product/43315/limpiahogar-aloe-vera-bosque-verde-concentrado-botella",
                                                "thumbnail":  "https://prod-mercadona.imgix.net/images/c52b4600f2909ecd893824fd423e58a7.jpg?fit=crop\u0026h=300\u0026w=300",
                                                "categories":  [
                                                                   {
                                                                       "id":  26,
                                                                       "name":  "Limpieza y hogar",
                                                                       "level":  0,
                                                                       "order":  374
                                                                   }
                                                               ],
                                                "display_name":  "Limpiahogar Aloe Vera Bosque Verde concentrado",
                                                "unavailable_from":  null,
                                                "price_instructions":  {
                                                                           "iva":  21,
                                                                           "is_new":  false,
                                                                           "is_pack":  false,
                                                                           "pack_size":  null,
                                                                           "unit_name":  null,
                                                                           "unit_size":  1.5,
                                                                           "bulk_price":  "1.43",
                                                                           "unit_price":  "2.15",
                                                                           "approx_size":  false,
                                                                           "size_format":  "l",
                                                                           "total_units":  null,
                                                                           "unit_selector":  true,
                                                                           "bunch_selector":  false,
                                                                           "drained_weight":  null,
                                                                           "selling_method":  0,
                                                                           "tax_percentage":  "21.000",
                                                                           "price_decreased":  false,
                                                                           "reference_price":  "1.434",
                                                                           "min_bunch_amount":  1.0,
                                                                           "reference_format":  "L",
                                                                           "previous_unit_price":  null,
                                                                           "increment_bunch_amount":  1.0
                                                                       },
                                                "unavailable_weekdays":  [

                                                                         ],
                                                "is_new_arrival":  false
                                            },
                                            {
                                                "id":  "35962",
                                                "slug":  "limpiador-concentrado-3-brujas-marmol-granito-ceramica-botella",
                                                "limit":  999,
                                                "badges":  {
                                                               "is_water":  false,
                                                               "requires_age_check":  false
                                                           },
                                                "status":  null,
                                                "packaging":  "Botella",
                                                "published":  true,
                                                "share_url":  "https://tienda.mercadona.es/product/35962/limpiador-concentrado-3-brujas-marmol-granito-ceramica-botella",
                                                "thumbnail":  "https://prod-mercadona.imgix.net/images/f439dcdb4e24ef2af2a9639aeec91eaf.jpg?fit=crop\u0026h=300\u0026w=300",
                                                "categories":  [
                                                                   {
                                                                       "id":  26,
                                                                       "name":  "Limpieza y hogar",
                                                                       "level":  0,
                                                                       "order":  374
                                                                   }
                                                               ],
                                                "display_name":  "Limpiador concentrado Las 3 Brujas",
                                                "unavailable_from":  null,
                                                "price_instructions":  {
                                                                           "iva":  21,
                                                                           "is_new":  false,
                                                                           "is_pack":  false,
                                                                           "pack_size":  null,
                                                                           "unit_name":  null,
                                                                           "unit_size":  1.0,
                                                                           "bulk_price":  "2.85",
                                                                           "unit_price":  "2.85",
                                                                           "approx_size":  false,
                                                                           "size_format":  "l",
                                                                           "total_units":  null,
                                                                           "unit_selector":  true,
                                                                           "bunch_selector":  false,
                                                                           "drained_weight":  null,
                                                                           "selling_method":  0,
                                                                           "tax_percentage":  "21.000",
                                                                           "price_decreased":  false,
                                                                           "reference_price":  "2.850",
                                                                           "min_bunch_amount":  1.0,
                                                                           "reference_format":  "L",
                                                                           "previous_unit_price":  null,
                                                                           "increment_bunch_amount":  1.0
                                                                       },
                                                "unavailable_weekdays":  [

                                                                         ],
                                                "is_new_arrival":  false
                                            },
                                            {
                                                "id":  "43329",
                                                "slug":  "limpiahogar-ph-neutro-bosque-verde-delicado-marmol-parquet-ceramica-botella",
                                                "limit":  999,
                                                "badges":  {
                                                               "is_water":  false,
                                                               "requires_age_check":  false
                                                           },
                                                "status":  null,
                                                "packaging":  "Botella",
                                                "published":  true,
                                                "share_url":  "https://tienda.mercadona.es/product/43329/limpiahogar-ph-neutro-bosque-verde-delicado-marmol-parquet-ceramica-botella",
                                                "thumbnail":  "https://prod-mercadona.imgix.net/images/807d06e34b181b1a99d14493d750e231.jpg?fit=crop\u0026h=300\u0026w=300",
                                                "categories":  [
                                                                   {
                                                                       "id":  26,
                                                                       "name":  "Limpieza y hogar",
                                                                       "level":  0,
                                                                       "order":  374
                                                                   }
                                                               ],
                                                "display_name":  "Limpiahogar PH Neutro Bosque Verde delicado",
                                                "unavailable_from":  null,
                                                "price_instructions":  {
                                                                           "iva":  null,
                                                                           "is_new":  false,
                                                                           "is_pack":  false,
                                                                           "pack_size":  null,
                                                                           "unit_name":  null,
                                                                           "unit_size":  1.5,
                                                                           "bulk_price":  "1.13",
                                                                           "unit_price":  "1.70",
                                                                           "approx_size":  false,
                                                                           "size_format":  "l",
                                                                           "total_units":  null,
                                                                           "unit_selector":  true,
                                                                           "bunch_selector":  false,
                                                                           "drained_weight":  null,
                                                                           "selling_method":  0,
                                                                           "tax_percentage":  "21.000",
                                                                           "price_decreased":  false,
                                                                           "reference_price":  "1.134",
                                                                           "min_bunch_amount":  1.0,
                                                                           "reference_format":  "L",
                                                                           "previous_unit_price":  null,
                                                                           "increment_bunch_amount":  1.0
                                                                       },
                                                "unavailable_weekdays":  [

                                                                         ],
                                                "is_new_arrival":  false
                                            },
                                            {
                                                "id":  "42204",
                                                "slug":  "limpiahogar-multiusos-pino-bosque-verde-liquido-con-alcohol-botella",
                                                "limit":  999,
                                                "badges":  {
                                                               "is_water":  false,
                                                               "requires_age_check":  false
                                                           },
                                                "status":  null,
                                                "packaging":  "Botella",
                                                "published":  true,
                                                "share_url":  "https://tienda.mercadona.es/product/42204/limpiahogar-multiusos-pino-bosque-verde-liquido-con-alcohol-botella",
                                                "thumbnail":  "https://prod-mercadona.imgix.net/images/90823c573de2b2c2e1b921a61deaf759.jpg?fit=crop\u0026h=300\u0026w=300",
                                                "categories":  [
                                                                   {
                                                                       "id":  26,
                                                                       "name":  "Limpieza y hogar",
                                                                       "level":  0,
                                                                       "order":  374
                                                                   }
                                                               ],
                                                "display_name":  "Limpiahogar Multiusos Pino Bosque Verde líquido",
                                                "unavailable_from":  null,
                                                "price_instructions":  {
                                                                           "iva":  null,
                                                                           "is_new":  false,
                                                                           "is_pack":  false,
                                                                           "pack_size":  null,
                                                                           "unit_name":  null,
                                                                           "unit_size":  1.5,
                                                                           "bulk_price":  "1.17",
                                                                           "unit_price":  "1.75",
                                                                           "approx_size":  false,
                                                                           "size_format":  "l",
                                                                           "total_units":  null,
                                                                           "unit_selector":  true,
                                                                           "bunch_selector":  false,
                                                                           "drained_weight":  null,
                                                                           "selling_method":  0,
                                                                           "tax_percentage":  "21.000",
                                                                           "price_decreased":  false,
                                                                           "reference_price":  "1.167",
                                                                           "min_bunch_amount":  1.0,
                                                                           "reference_format":  "L",
                                                                           "previous_unit_price":  null,
                                                                           "increment_bunch_amount":  1.0
                                                                       },
                                                "unavailable_weekdays":  [

                                                                         ],
                                                "is_new_arrival":  false
                                            },
                                            {
                                                "id":  "43301",
                                                "slug":  "limpiahogar-con-lejia-bosque-verde-gel-botella",
                                                "limit":  999,
                                                "badges":  {
                                                               "is_water":  false,
                                                               "requires_age_check":  false
                                                           },
                                                "status":  null,
                                                "packaging":  "Botella",
                                                "published":  true,
                                                "share_url":  "https://tienda.mercadona.es/product/43301/limpiahogar-con-lejia-bosque-verde-gel-botella",
                                                "thumbnail":  "https://prod-mercadona.imgix.net/images/dabeb80bde7b6875bc771b7aa8f91efb.jpg?fit=crop\u0026h=300\u0026w=300",
                                                "categories":  [
                                                                   {
                                                                       "id":  26,
                                                                       "name":  "Limpieza y hogar",
                                                                       "level":  0,
                                                                       "order":  374
                                                                   }
                                                               ],
                                                "display_name":  "Limpiahogar con lejía Bosque Verde en gel",
                                                "unavailable_from":  null,
                                                "price_instructions":  {
                                                                           "iva":  21,
                                                                           "is_new":  false,
                                                                           "is_pack":  false,
                                                                           "pack_size":  null,
                                                                           "unit_name":  null,
                                                                           "unit_size":  1.5,
                                                                           "bulk_price":  "1.27",
                                                                           "unit_price":  "1.90",
                                                                           "approx_size":  false,
                                                                           "size_format":  "l",
                                                                           "total_units":  null,
                                                                           "unit_selector":  true,
                                                                           "bunch_selector":  false,
                                                                           "drained_weight":  null,
                                                                           "selling_method":  0,
                                                                           "tax_percentage":  "21.000",
                                                                           "price_decreased":  false,
                                                                           "reference_price":  "1.267",
                                                                           "min_bunch_amount":  1.0,
                                                                           "reference_format":  "L",
                                                                           "previous_unit_price":  null,
                                                                           "increment_bunch_amount":  1.0
                                                                       },
                                                "unavailable_weekdays":  [

                                                                         ],
                                                "is_new_arrival":  false
                                            },
                                            {
                                                "id":  "43338",
                                                "slug":  "limpiahogar-oxi-active-bosque-verde-sin-lejia-botella",
                                                "limit":  999,
                                                "badges":  {
                                                               "is_water":  false,
                                                               "requires_age_check":  false
                                                           },
                                                "status":  null,
                                                "packaging":  "Botella",
                                                "published":  true,
                                                "share_url":  "https://tienda.mercadona.es/product/43338/limpiahogar-oxi-active-bosque-verde-sin-lejia-botella",
                                                "thumbnail":  "https://prod-mercadona.imgix.net/images/d2d88fef43fc70c7f6a18d1cb4ff428a.jpg?fit=crop\u0026h=300\u0026w=300",
                                                "categories":  [
                                                                   {
                                                                       "id":  26,
                                                                       "name":  "Limpieza y hogar",
                                                                       "level":  0,
                                                                       "order":  374
                                                                   }
                                                               ],
                                                "display_name":  "Limpiahogar Oxi Active Bosque Verde sin lejía",
                                                "unavailable_from":  null,
                                                "price_instructions":  {
                                                                           "iva":  21,
                                                                           "is_new":  false,
                                                                           "is_pack":  false,
                                                                           "pack_size":  null,
                                                                           "unit_name":  null,
                                                                           "unit_size":  1.0,
                                                                           "bulk_price":  "1.35",
                                                                           "unit_price":  "1.35",
                                                                           "approx_size":  false,
                                                                           "size_format":  "l",
                                                                           "total_units":  null,
                                                                           "unit_selector":  true,
                                                                           "bunch_selector":  false,
                                                                           "drained_weight":  null,
                                                                           "selling_method":  0,
                                                                           "tax_percentage":  "21.000",
                                                                           "price_decreased":  false,
                                                                           "reference_price":  "1.350",
                                                                           "min_bunch_amount":  1.0,
                                                                           "reference_format":  "L",
                                                                           "previous_unit_price":  null,
                                                                           "increment_bunch_amount":  1.0
                                                                       },
                                                "unavailable_weekdays":  [

                                                                         ],
                                                "is_new_arrival":  false
                                            },
                                            {
                                                "id":  "44262",
                                                "slug":  "limpiahogar-desinfectante-bosque-verde-sin-lejia-botella",
                                                "limit":  999,
                                                "badges":  {
                                                               "is_water":  false,
                                                               "requires_age_check":  false
                                                           },
                                                "status":  null,
                                                "packaging":  "Botella",
                                                "published":  true,
                                                "share_url":  "https://tienda.mercadona.es/product/44262/limpiahogar-desinfectante-bosque-verde-sin-lejia-botella",
                                                "thumbnail":  "https://prod-mercadona.imgix.net/images/b09ae2460bbbd2320b423bc7281b3772.jpg?fit=crop\u0026h=300\u0026w=300",
                                                "categories":  [
                                                                   {
                                                                       "id":  26,
                                                                       "name":  "Limpieza y hogar",
                                                                       "level":  0,
                                                                       "order":  374
                                                                   }
                                                               ],
                                                "display_name":  "Limpiahogar desinfectante Bosque Verde",
                                                "unavailable_from":  null,
                                                "price_instructions":  {
                                                                           "iva":  21,
                                                                           "is_new":  false,
                                                                           "is_pack":  false,
                                                                           "pack_size":  null,
                                                                           "unit_name":  null,
                                                                           "unit_size":  1.5,
                                                                           "bulk_price":  "1.40",
                                                                           "unit_price":  "2.10",
                                                                           "approx_size":  false,
                                                                           "size_format":  "l",
                                                                           "total_units":  null,
                                                                           "unit_selector":  true,
                                                                           "bunch_selector":  false,
                                                                           "drained_weight":  null,
                                                                           "selling_method":  0,
                                                                           "tax_percentage":  "21.000",
                                                                           "price_decreased":  false,
                                                                           "reference_price":  "1.400",
                                                                           "min_bunch_amount":  1.0,
                                                                           "reference_format":  "L",
                                                                           "previous_unit_price":  null,
                                                                           "increment_bunch_amount":  1.0
                                                                       },
                                                "unavailable_weekdays":  [

                                                                         ],
                                                "is_new_arrival":  false
                                            },
                                            {
                                                "id":  "44019",
                                                "slug":  "multiusos-desinfectante-antibacterias-bosque-verde-sin-lejia-con-pistola-botella",
                                                "limit":  999,
                                                "badges":  {
                                                               "is_water":  false,
                                                               "requires_age_check":  false
                                                           },
                                                "status":  null,
                                                "packaging":  "Botella",
                                                "published":  true,
                                                "share_url":  "https://tienda.mercadona.es/product/44019/multiusos-desinfectante-antibacterias-bosque-verde-sin-lejia-con-pistola-botella",
                                                "thumbnail":  "https://prod-mercadona.imgix.net/images/d41d4613ade2dde055147ce6a8efe206.jpg?fit=crop\u0026h=300\u0026w=300",
                                                "categories":  [
                                                                   {
                                                                       "id":  26,
                                                                       "name":  "Limpieza y hogar",
                                                                       "level":  0,
                                                                       "order":  374
                                                                   }
                                                               ],
                                                "display_name":  "Multiusos Desinfectante antibacterias Bosque Verde",
                                                "unavailable_from":  null,
                                                "price_instructions":  {
                                                                           "iva":  21,
                                                                           "is_new":  false,
                                                                           "is_pack":  false,
                                                                           "pack_size":  null,
                                                                           "unit_name":  null,
                                                                           "unit_size":  0.75,
                                                                           "bulk_price":  "2.60",
                                                                           "unit_price":  "1.95",
                                                                           "approx_size":  false,
                                                                           "size_format":  "l",
                                                                           "total_units":  null,
                                                                           "unit_selector":  true,
                                                                           "bunch_selector":  false,
                                                                           "drained_weight":  null,
                                                                           "selling_method":  0,
                                                                           "tax_percentage":  "21.000",
                                                                           "price_decreased":  false,
                                                                           "reference_price":  "2.600",
                                                                           "min_bunch_amount":  1.0,
                                                                           "reference_format":  "L",
                                                                           "previous_unit_price":  null,
                                                                           "increment_bunch_amount":  1.0
                                                                       },
                                                "unavailable_weekdays":  [

                                                                         ],
                                                "is_new_arrival":  false
                                            },
                                            {
                                                "id":  "43112",
                                                "slug":  "70-alcohol-limpieza-hogar-bosque-verde-perfumado-con-pistola-botella",
                                                "limit":  999,
                                                "badges":  {
                                                               "is_water":  false,
                                                               "requires_age_check":  false
                                                           },
                                                "status":  null,
                                                "packaging":  "Botella",
                                                "published":  true,
                                                "share_url":  "https://tienda.mercadona.es/product/43112/70-alcohol-limpieza-hogar-bosque-verde-perfumado-con-pistola-botella",
                                                "thumbnail":  "https://prod-mercadona.imgix.net/images/f8f5be02ca76a6bbcde467b440392a24.jpg?fit=crop\u0026h=300\u0026w=300",
                                                "categories":  [
                                                                   {
                                                                       "id":  26,
                                                                       "name":  "Limpieza y hogar",
                                                                       "level":  0,
                                                                       "order":  374
                                                                   }
                                                               ],
                                                "display_name":  "70% Alcohol limpieza hogar Bosque Verde",
                                                "unavailable_from":  null,
                                                "price_instructions":  {
                                                                           "iva":  21,
                                                                           "is_new":  false,
                                                                           "is_pack":  false,
                                                                           "pack_size":  null,
                                                                           "unit_name":  null,
                                                                           "unit_size":  0.75,
                                                                           "bulk_price":  "3.47",
                                                                           "unit_price":  "2.60",
                                                                           "approx_size":  false,
                                                                           "size_format":  "l",
                                                                           "total_units":  null,
                                                                           "unit_selector":  true,
                                                                           "bunch_selector":  false,
                                                                           "drained_weight":  null,
                                                                           "selling_method":  0,
                                                                           "tax_percentage":  "21.000",
                                                                           "price_decreased":  false,
                                                                           "reference_price":  "3.467",
                                                                           "min_bunch_amount":  1.0,
                                                                           "reference_format":  "L",
                                                                           "previous_unit_price":  null,
                                                                           "increment_bunch_amount":  1.0
                                                                       },
                                                "unavailable_weekdays":  [

                                                                         ],
                                                "is_new_arrival":  false
                                            }
                                        ]
                       }
                   ],
    "next_category":  {
                          "id":  231,
                          "name":  "Limpieza baño y WC"
                      }
}
