{
    "id":  238,
    "name":  "Papel higiénico y celulosa",
    "order":  374,
    "layout":  1,
    "published":  true,
    "is_extended":  false,
    "categories":  [
                       {
                           "id":  838,
                           "name":  "Servilletas",
                           "order":  374,
                           "layout":  2,
                           "published":  true,
                           "is_extended":  false,
                           "image":  null,
                           "subtitle":  null,
                           "products":  [
                                            {
                                                "id":  "49544",
                                                "slug":  "servilleta-papel-bosque-verde-1-capa-30-x-30-cm-paquete",
                                                "limit":  999,
                                                "badges":  {
                                                               "is_water":  false,
                                                               "requires_age_check":  false
                                                           },
                                                "status":  null,
                                                "packaging":  "Paquete",
                                                "published":  true,
                                                "share_url":  "https://tienda.mercadona.es/product/49544/servilleta-papel-bosque-verde-1-capa-30-x-30-cm-paquete",
                                                "thumbnail":  "https://prod-mercadona.imgix.net/images/bfcc81e168ee5a8e58f26e2ba67dfb40.jpg?fit=crop\u0026h=300\u0026w=300",
                                                "categories":  [
                                                                   {
                                                                       "id":  26,
                                                                       "name":  "Limpieza y hogar",
                                                                       "level":  0,
                                                                       "order":  374
                                                                   }
                                                               ],
                                                "display_name":  "Servilleta papel Bosque Verde",
                                                "unavailable_from":  null,
                                                "price_instructions":  {
                                                                           "iva":  null,
                                                                           "is_new":  false,
                                                                           "is_pack":  false,
                                                                           "pack_size":  null,
                                                                           "unit_name":  null,
                                                                           "unit_size":  200.0,
                                                                           "bulk_price":  "0.01",
                                                                           "unit_price":  "1.15",
                                                                           "approx_size":  false,
                                                                           "size_format":  "ud",
                                                                           "total_units":  null,
                                                                           "unit_selector":  true,
                                                                           "bunch_selector":  false,
                                                                           "drained_weight":  null,
                                                                           "selling_method":  0,
                                                                           "tax_percentage":  "21.000",
                                                                           "price_decreased":  false,
                                                                           "reference_price":  "0.006",
                                                                           "min_bunch_amount":  1.0,
                                                                           "reference_format":  "ud",
                                                                           "previous_unit_price":  null,
                                                                           "increment_bunch_amount":  1.0
                                                                       },
                                                "unavailable_weekdays":  [

                                                                         ],
                                                "is_new_arrival":  false
                                            },
                                            {
                                                "id":  "49710",
                                                "slug":  "servilleta-papel-decorada-resistente-bosque-verde-2-capas-33-x-32-cm-paquete",
                                                "limit":  999,
                                                "badges":  {
                                                               "is_water":  false,
                                                               "requires_age_check":  false
                                                           },
                                                "status":  null,
                                                "packaging":  "Paquete",
                                                "published":  true,
                                                "share_url":  "https://tienda.mercadona.es/product/49710/servilleta-papel-decorada-resistente-bosque-verde-2-capas-33-x-32-cm-paquete",
                                                "thumbnail":  "https://prod-mercadona.imgix.net/images/be92c287be9f035ad4938c6280743b42.jpg?fit=crop\u0026h=300\u0026w=300",
                                                "categories":  [
                                                                   {
                                                                       "id":  26,
                                                                       "name":  "Limpieza y hogar",
                                                                       "level":  0,
                                                                       "order":  374
                                                                   }
                                                               ],
                                                "display_name":  "Servilleta papel decorada Resistente Bosque Verde",
                                                "unavailable_from":  null,
                                                "price_instructions":  {
                                                                           "iva":  null,
                                                                           "is_new":  false,
                                                                           "is_pack":  false,
                                                                           "pack_size":  null,
                                                                           "unit_name":  null,
                                                                           "unit_size":  100.0,
                                                                           "bulk_price":  "0.02",
                                                                           "unit_price":  "2.05",
                                                                           "approx_size":  false,
                                                                           "size_format":  "ud",
                                                                           "total_units":  null,
                                                                           "unit_selector":  true,
                                                                           "bunch_selector":  false,
                                                                           "drained_weight":  null,
                                                                           "selling_method":  0,
                                                                           "tax_percentage":  "21.000",
                                                                           "price_decreased":  false,
                                                                           "reference_price":  "0.021",
                                                                           "min_bunch_amount":  1.0,
                                                                           "reference_format":  "ud",
                                                                           "previous_unit_price":  null,
                                                                           "increment_bunch_amount":  1.0
                                                                       },
                                                "unavailable_weekdays":  [

                                                                         ],
                                                "is_new_arrival":  false
                                            },
                                            {
                                                "id":  "49701",
                                                "slug":  "servilleta-papel-cocktail-bosque-verde-2-capas-22-x-22-cm-paquete",
                                                "limit":  999,
                                                "badges":  {
                                                               "is_water":  false,
                                                               "requires_age_check":  false
                                                           },
                                                "status":  null,
                                                "packaging":  "Paquete",
                                                "published":  true,
                                                "share_url":  "https://tienda.mercadona.es/product/49701/servilleta-papel-cocktail-bosque-verde-2-capas-22-x-22-cm-paquete",
                                                "thumbnail":  "https://prod-mercadona.imgix.net/images/b1f0583de198e0fe8a5699f056e7255a.jpg?fit=crop\u0026h=300\u0026w=300",
                                                "categories":  [
                                                                   {
                                                                       "id":  26,
                                                                       "name":  "Limpieza y hogar",
                                                                       "level":  0,
                                                                       "order":  374
                                                                   }
                                                               ],
                                                "display_name":  "Servilleta papel Cocktail Bosque Verde",
                                                "unavailable_from":  null,
                                                "price_instructions":  {
                                                                           "iva":  21,
                                                                           "is_new":  false,
                                                                           "is_pack":  false,
                                                                           "pack_size":  null,
                                                                           "unit_name":  null,
                                                                           "unit_size":  200.0,
                                                                           "bulk_price":  "0.01",
                                                                           "unit_price":  "2.10",
                                                                           "approx_size":  false,
                                                                           "size_format":  "ud",
                                                                           "total_units":  null,
                                                                           "unit_selector":  true,
                                                                           "bunch_selector":  false,
                                                                           "drained_weight":  null,
                                                                           "selling_method":  0,
                                                                           "tax_percentage":  "21.000",
                                                                           "price_decreased":  false,
                                                                           "reference_price":  "0.011",
                                                                           "min_bunch_amount":  1.0,
                                                                           "reference_format":  "ud",
                                                                           "previous_unit_price":  null,
                                                                           "increment_bunch_amount":  1.0
                                                                       },
                                                "unavailable_weekdays":  [

                                                                         ],
                                                "is_new_arrival":  false
                                            },
                                            {
                                                "id":  "49589",
                                                "slug":  "servilleta-papel-suave-bosque-verde-2-capas-33-x-32-cm-paquete",
                                                "limit":  999,
                                                "badges":  {
                                                               "is_water":  false,
                                                               "requires_age_check":  false
                                                           },
                                                "status":  null,
                                                "packaging":  "Paquete",
                                                "published":  true,
                                                "share_url":  "https://tienda.mercadona.es/product/49589/servilleta-papel-suave-bosque-verde-2-capas-33-x-32-cm-paquete",
                                                "thumbnail":  "https://prod-mercadona.imgix.net/images/8b47fff99894d468256430fb5afb856b.jpg?fit=crop\u0026h=300\u0026w=300",
                                                "categories":  [
                                                                   {
                                                                       "id":  26,
                                                                       "name":  "Limpieza y hogar",
                                                                       "level":  0,
                                                                       "order":  374
                                                                   }
                                                               ],
                                                "display_name":  "Servilleta papel suave Bosque Verde",
                                                "unavailable_from":  null,
                                                "price_instructions":  {
                                                                           "iva":  null,
                                                                           "is_new":  false,
                                                                           "is_pack":  false,
                                                                           "pack_size":  null,
                                                                           "unit_name":  null,
                                                                           "unit_size":  100.0,
                                                                           "bulk_price":  "0.02",
                                                                           "unit_price":  "1.65",
                                                                           "approx_size":  false,
                                                                           "size_format":  "ud",
                                                                           "total_units":  null,
                                                                           "unit_selector":  true,
                                                                           "bunch_selector":  false,
                                                                           "drained_weight":  null,
                                                                           "selling_method":  0,
                                                                           "tax_percentage":  "21.000",
                                                                           "price_decreased":  false,
                                                                           "reference_price":  "0.017",
                                                                           "min_bunch_amount":  1.0,
                                                                           "reference_format":  "ud",
                                                                           "previous_unit_price":  null,
                                                                           "increment_bunch_amount":  1.0
                                                                       },
                                                "unavailable_weekdays":  [

                                                                         ],
                                                "is_new_arrival":  false
                                            }
                                        ]
                       },
                       {
                           "id":  756,
                           "name":  "Rollo cocina",
                           "order":  374,
                           "layout":  2,
                           "published":  true,
                           "is_extended":  false,
                           "image":  null,
                           "subtitle":  null,
                           "products":  [
                                            {
                                                "id":  "49619",
                                                "slug":  "papel-hogar-compacto-absorbente-bosque-verde-paquete",
                                                "limit":  999,
                                                "badges":  {
                                                               "is_water":  false,
                                                               "requires_age_check":  false
                                                           },
                                                "status":  null,
                                                "packaging":  "Paquete",
                                                "published":  true,
                                                "share_url":  "https://tienda.mercadona.es/product/49619/papel-hogar-compacto-absorbente-bosque-verde-paquete",
                                                "thumbnail":  "https://prod-mercadona.imgix.net/images/c2b185d672f992dd957400a4f39d1f5b.jpg?fit=crop\u0026h=300\u0026w=300",
                                                "categories":  [
                                                                   {
                                                                       "id":  26,
                                                                       "name":  "Limpieza y hogar",
                                                                       "level":  0,
                                                                       "order":  374
                                                                   }
                                                               ],
                                                "display_name":  "Papel hogar Compacto Absorbente Bosque Verde",
                                                "unavailable_from":  null,
                                                "price_instructions":  {
                                                                           "iva":  null,
                                                                           "is_new":  false,
                                                                           "is_pack":  false,
                                                                           "pack_size":  null,
                                                                           "unit_name":  "servicios",
                                                                           "unit_size":  3.0,
                                                                           "bulk_price":  "0.78",
                                                                           "unit_price":  "2.35",
                                                                           "approx_size":  false,
                                                                           "size_format":  "ud",
                                                                           "total_units":  300,
                                                                           "unit_selector":  true,
                                                                           "bunch_selector":  false,
                                                                           "drained_weight":  null,
                                                                           "selling_method":  0,
                                                                           "tax_percentage":  "21.000",
                                                                           "price_decreased":  false,
                                                                           "reference_price":  "0.784",
                                                                           "min_bunch_amount":  1.0,
                                                                           "reference_format":  "ud",
                                                                           "previous_unit_price":  null,
                                                                           "increment_bunch_amount":  1.0
                                                                       },
                                                "unavailable_weekdays":  [

                                                                         ],
                                                "is_new_arrival":  false
                                            },
                                            {
                                                "id":  "49173",
                                                "slug":  "papel-multiusos-resistente-bosque-verde-paquete",
                                                "limit":  999,
                                                "badges":  {
                                                               "is_water":  false,
                                                               "requires_age_check":  false
                                                           },
                                                "status":  null,
                                                "packaging":  "Paquete",
                                                "published":  true,
                                                "share_url":  "https://tienda.mercadona.es/product/49173/papel-multiusos-resistente-bosque-verde-paquete",
                                                "thumbnail":  "https://prod-mercadona.imgix.net/images/68a9193c73346578a71a679044434f6f.jpg?fit=crop\u0026h=300\u0026w=300",
                                                "categories":  [
                                                                   {
                                                                       "id":  26,
                                                                       "name":  "Limpieza y hogar",
                                                                       "level":  0,
                                                                       "order":  374
                                                                   }
                                                               ],
                                                "display_name":  "Papel Multiusos Resistente Bosque Verde",
                                                "unavailable_from":  null,
                                                "price_instructions":  {
                                                                           "iva":  null,
                                                                           "is_new":  false,
                                                                           "is_pack":  false,
                                                                           "pack_size":  null,
                                                                           "unit_name":  "servicios",
                                                                           "unit_size":  1.0,
                                                                           "bulk_price":  "3.70",
                                                                           "unit_price":  "3.70",
                                                                           "approx_size":  false,
                                                                           "size_format":  "ud",
                                                                           "total_units":  600,
                                                                           "unit_selector":  true,
                                                                           "bunch_selector":  false,
                                                                           "drained_weight":  null,
                                                                           "selling_method":  0,
                                                                           "tax_percentage":  "21.000",
                                                                           "price_decreased":  false,
                                                                           "reference_price":  "3.700",
                                                                           "min_bunch_amount":  1.0,
                                                                           "reference_format":  "ud",
                                                                           "previous_unit_price":  null,
                                                                           "increment_bunch_amount":  1.0
                                                                       },
                                                "unavailable_weekdays":  [

                                                                         ],
                                                "is_new_arrival":  false
                                            },
                                            {
                                                "id":  "49176",
                                                "slug":  "papel-cocina-gigante-absorbente-bosque-verde-paquete",
                                                "limit":  999,
                                                "badges":  {
                                                               "is_water":  false,
                                                               "requires_age_check":  false
                                                           },
                                                "status":  null,
                                                "packaging":  "Paquete",
                                                "published":  true,
                                                "share_url":  "https://tienda.mercadona.es/product/49176/papel-cocina-gigante-absorbente-bosque-verde-paquete",
                                                "thumbnail":  "https://prod-mercadona.imgix.net/images/1754c20c79fab74549f3b7f5a05bfb80.jpg?fit=crop\u0026h=300\u0026w=300",
                                                "categories":  [
                                                                   {
                                                                       "id":  26,
                                                                       "name":  "Limpieza y hogar",
                                                                       "level":  0,
                                                                       "order":  374
                                                                   }
                                                               ],
                                                "display_name":  "Papel cocina Gigante Absorbente Bosque Verde",
                                                "unavailable_from":  null,
                                                "price_instructions":  {
                                                                           "iva":  null,
                                                                           "is_new":  false,
                                                                           "is_pack":  false,
                                                                           "pack_size":  null,
                                                                           "unit_name":  "servicios",
                                                                           "unit_size":  1.0,
                                                                           "bulk_price":  "2.95",
                                                                           "unit_price":  "2.95",
                                                                           "approx_size":  false,
                                                                           "size_format":  "ud",
                                                                           "total_units":  375,
                                                                           "unit_selector":  true,
                                                                           "bunch_selector":  false,
                                                                           "drained_weight":  null,
                                                                           "selling_method":  0,
                                                                           "tax_percentage":  "21.000",
                                                                           "price_decreased":  false,
                                                                           "reference_price":  "2.950",
                                                                           "min_bunch_amount":  1.0,
                                                                           "reference_format":  "ud",
                                                                           "previous_unit_price":  null,
                                                                           "increment_bunch_amount":  1.0
                                                                       },
                                                "unavailable_weekdays":  [

                                                                         ],
                                                "is_new_arrival":  false
                                            }
                                        ]
                       },
                       {
                           "id":  755,
                           "name":  "Papel higiénico",
                           "order":  374,
                           "layout":  2,
                           "published":  true,
                           "is_extended":  false,
                           "image":  null,
                           "subtitle":  null,
                           "products":  [
                                            {
                                                "id":  "47818",
                                                "slug":  "papel-higienico-doble-rollo-bosque-verde-paquete",
                                                "limit":  999,
                                                "badges":  {
                                                               "is_water":  false,
                                                               "requires_age_check":  false
                                                           },
                                                "status":  null,
                                                "packaging":  "Paquete",
                                                "published":  true,
                                                "share_url":  "https://tienda.mercadona.es/product/47818/papel-higienico-doble-rollo-bosque-verde-paquete",
                                                "thumbnail":  "https://prod-mercadona.imgix.net/images/2114d726e660470b9eea54e72125280a.jpg?fit=crop\u0026h=300\u0026w=300",
                                                "categories":  [
                                                                   {
                                                                       "id":  26,
                                                                       "name":  "Limpieza y hogar",
                                                                       "level":  0,
                                                                       "order":  374
                                                                   }
                                                               ],
                                                "display_name":  "Papel higiénico Doble Rollo Bosque Verde",
                                                "unavailable_from":  null,
                                                "price_instructions":  {
                                                                           "iva":  null,
                                                                           "is_new":  false,
                                                                           "is_pack":  false,
                                                                           "pack_size":  null,
                                                                           "unit_name":  "rollos",
                                                                           "unit_size":  1.0,
                                                                           "bulk_price":  "0.38",
                                                                           "unit_price":  "4.60",
                                                                           "approx_size":  false,
                                                                           "size_format":  "ud",
                                                                           "total_units":  12,
                                                                           "unit_selector":  true,
                                                                           "bunch_selector":  false,
                                                                           "drained_weight":  null,
                                                                           "selling_method":  0,
                                                                           "tax_percentage":  "21.000",
                                                                           "price_decreased":  false,
                                                                           "reference_price":  "0.384",
                                                                           "min_bunch_amount":  1.0,
                                                                           "reference_format":  "ud",
                                                                           "previous_unit_price":  null,
                                                                           "increment_bunch_amount":  1.0
                                                                       },
                                                "unavailable_weekdays":  [

                                                                         ],
                                                "is_new_arrival":  false
                                            },
                                            {
                                                "id":  "47819",
                                                "slug":  "papel-higienico-doble-rollo-bosque-verde-paquete",
                                                "limit":  999,
                                                "badges":  {
                                                               "is_water":  false,
                                                               "requires_age_check":  false
                                                           },
                                                "status":  null,
                                                "packaging":  "Paquete",
                                                "published":  true,
                                                "share_url":  "https://tienda.mercadona.es/product/47819/papel-higienico-doble-rollo-bosque-verde-paquete",
                                                "thumbnail":  "https://prod-mercadona.imgix.net/images/7dceeae4ce17bf0c89c9e02330457a4a.jpg?fit=crop\u0026h=300\u0026w=300",
                                                "categories":  [
                                                                   {
                                                                       "id":  26,
                                                                       "name":  "Limpieza y hogar",
                                                                       "level":  0,
                                                                       "order":  374
                                                                   }
                                                               ],
                                                "display_name":  "Papel higiénico Doble Rollo Bosque Verde",
                                                "unavailable_from":  null,
                                                "price_instructions":  {
                                                                           "iva":  null,
                                                                           "is_new":  false,
                                                                           "is_pack":  false,
                                                                           "pack_size":  null,
                                                                           "unit_name":  "rollos",
                                                                           "unit_size":  1.0,
                                                                           "bulk_price":  "0.39",
                                                                           "unit_price":  "2.35",
                                                                           "approx_size":  false,
                                                                           "size_format":  "ud",
                                                                           "total_units":  6,
                                                                           "unit_selector":  true,
                                                                           "bunch_selector":  false,
                                                                           "drained_weight":  null,
                                                                           "selling_method":  0,
                                                                           "tax_percentage":  "21.000",
                                                                           "price_decreased":  false,
                                                                           "reference_price":  "0.392",
                                                                           "min_bunch_amount":  1.0,
                                                                           "reference_format":  "ud",
                                                                           "previous_unit_price":  null,
                                                                           "increment_bunch_amount":  1.0
                                                                       },
                                                "unavailable_weekdays":  [

                                                                         ],
                                                "is_new_arrival":  false
                                            },
                                            {
                                                "id":  "47835",
                                                "slug":  "papel-higienico-doble-hoja-bosque-verde-paquete",
                                                "limit":  999,
                                                "badges":  {
                                                               "is_water":  false,
                                                               "requires_age_check":  false
                                                           },
                                                "status":  null,
                                                "packaging":  "Paquete",
                                                "published":  true,
                                                "share_url":  "https://tienda.mercadona.es/product/47835/papel-higienico-doble-hoja-bosque-verde-paquete",
                                                "thumbnail":  "https://prod-mercadona.imgix.net/images/8629429b287c46d53db4df0f83fee72a.jpg?fit=crop\u0026h=300\u0026w=300",
                                                "categories":  [
                                                                   {
                                                                       "id":  26,
                                                                       "name":  "Limpieza y hogar",
                                                                       "level":  0,
                                                                       "order":  374
                                                                   }
                                                               ],
                                                "display_name":  "Papel higiénico doble hoja Bosque Verde",
                                                "unavailable_from":  null,
                                                "price_instructions":  {
                                                                           "iva":  null,
                                                                           "is_new":  false,
                                                                           "is_pack":  false,
                                                                           "pack_size":  null,
                                                                           "unit_name":  "rollos",
                                                                           "unit_size":  1.0,
                                                                           "bulk_price":  "0.20",
                                                                           "unit_price":  "2.35",
                                                                           "approx_size":  false,
                                                                           "size_format":  "ud",
                                                                           "total_units":  12,
                                                                           "unit_selector":  true,
                                                                           "bunch_selector":  false,
                                                                           "drained_weight":  null,
                                                                           "selling_method":  0,
                                                                           "tax_percentage":  "21.000",
                                                                           "price_decreased":  false,
                                                                           "reference_price":  "0.196",
                                                                           "min_bunch_amount":  1.0,
                                                                           "reference_format":  "ud",
                                                                           "previous_unit_price":  "        2.50",
                                                                           "increment_bunch_amount":  1.0
                                                                       },
                                                "unavailable_weekdays":  [

                                                                         ],
                                                "is_new_arrival":  false
                                            },
                                            {
                                                "id":  "12912",
                                                "slug":  "papel-higienico-suave-bosque-verde-4-capas-paquete",
                                                "limit":  999,
                                                "badges":  {
                                                               "is_water":  false,
                                                               "requires_age_check":  false
                                                           },
                                                "status":  null,
                                                "packaging":  "Paquete",
                                                "published":  true,
                                                "share_url":  "https://tienda.mercadona.es/product/12912/papel-higienico-suave-bosque-verde-4-capas-paquete",
                                                "thumbnail":  "https://prod-mercadona.imgix.net/images/c101fb054823f64dfbece29949dd8e23.jpg?fit=crop\u0026h=300\u0026w=300",
                                                "categories":  [
                                                                   {
                                                                       "id":  26,
                                                                       "name":  "Limpieza y hogar",
                                                                       "level":  0,
                                                                       "order":  374
                                                                   }
                                                               ],
                                                "display_name":  "Papel higiénico Suave Bosque Verde",
                                                "unavailable_from":  null,
                                                "price_instructions":  {
                                                                           "iva":  null,
                                                                           "is_new":  false,
                                                                           "is_pack":  false,
                                                                           "pack_size":  null,
                                                                           "unit_name":  "rollos",
                                                                           "unit_size":  1.0,
                                                                           "bulk_price":  "0.46",
                                                                           "unit_price":  "3.70",
                                                                           "approx_size":  false,
                                                                           "size_format":  "ud",
                                                                           "total_units":  8,
                                                                           "unit_selector":  true,
                                                                           "bunch_selector":  false,
                                                                           "drained_weight":  null,
                                                                           "selling_method":  0,
                                                                           "tax_percentage":  "21.000",
                                                                           "price_decreased":  false,
                                                                           "reference_price":  "0.463",
                                                                           "min_bunch_amount":  1.0,
                                                                           "reference_format":  "ud",
                                                                           "previous_unit_price":  null,
                                                                           "increment_bunch_amount":  1.0
                                                                       },
                                                "unavailable_weekdays":  [

                                                                         ],
                                                "is_new_arrival":  false
                                            },
                                            {
                                                "id":  "47293",
                                                "slug":  "papel-higienico-humedo-wc-bosque-verde-con-aloe-vera-camomila-paquete",
                                                "limit":  999,
                                                "badges":  {
                                                               "is_water":  false,
                                                               "requires_age_check":  false
                                                           },
                                                "status":  null,
                                                "packaging":  "Paquete",
                                                "published":  true,
                                                "share_url":  "https://tienda.mercadona.es/product/47293/papel-higienico-humedo-wc-bosque-verde-con-aloe-vera-camomila-paquete",
                                                "thumbnail":  "https://prod-mercadona.imgix.net/images/286f24c12adab78274a9cb5cca4f1278.jpg?fit=crop\u0026h=300\u0026w=300",
                                                "categories":  [
                                                                   {
                                                                       "id":  26,
                                                                       "name":  "Limpieza y hogar",
                                                                       "level":  0,
                                                                       "order":  374
                                                                   }
                                                               ],
                                                "display_name":  "Papel higiénico húmedo WC Bosque Verde",
                                                "unavailable_from":  null,
                                                "price_instructions":  {
                                                                           "iva":  21,
                                                                           "is_new":  false,
                                                                           "is_pack":  false,
                                                                           "pack_size":  null,
                                                                           "unit_name":  "ud.",
                                                                           "unit_size":  1.0,
                                                                           "bulk_price":  "0.05",
                                                                           "unit_price":  "0.80",
                                                                           "approx_size":  false,
                                                                           "size_format":  "ud",
                                                                           "total_units":  15,
                                                                           "unit_selector":  true,
                                                                           "bunch_selector":  false,
                                                                           "drained_weight":  null,
                                                                           "selling_method":  0,
                                                                           "tax_percentage":  "21.000",
                                                                           "price_decreased":  false,
                                                                           "reference_price":  "0.054",
                                                                           "min_bunch_amount":  1.0,
                                                                           "reference_format":  "ud",
                                                                           "previous_unit_price":  null,
                                                                           "increment_bunch_amount":  1.0
                                                                       },
                                                "unavailable_weekdays":  [

                                                                         ],
                                                "is_new_arrival":  false
                                            },
                                            {
                                                "id":  "47291",
                                                "slug":  "papel-higienico-humedo-wc-bosque-verde-con-aloe-vera-camomila-paquete",
                                                "limit":  999,
                                                "badges":  {
                                                               "is_water":  false,
                                                               "requires_age_check":  false
                                                           },
                                                "status":  null,
                                                "packaging":  "Paquete",
                                                "published":  true,
                                                "share_url":  "https://tienda.mercadona.es/product/47291/papel-higienico-humedo-wc-bosque-verde-con-aloe-vera-camomila-paquete",
                                                "thumbnail":  "https://prod-mercadona.imgix.net/images/d6ab8e94cf1adb75cb470a93d2def3df.jpg?fit=crop\u0026h=300\u0026w=300",
                                                "categories":  [
                                                                   {
                                                                       "id":  26,
                                                                       "name":  "Limpieza y hogar",
                                                                       "level":  0,
                                                                       "order":  374
                                                                   }
                                                               ],
                                                "display_name":  "Papel higiénico húmedo WC Bosque Verde",
                                                "unavailable_from":  null,
                                                "price_instructions":  {
                                                                           "iva":  21,
                                                                           "is_new":  false,
                                                                           "is_pack":  false,
                                                                           "pack_size":  null,
                                                                           "unit_name":  null,
                                                                           "unit_size":  100.0,
                                                                           "bulk_price":  "0.02",
                                                                           "unit_price":  "1.55",
                                                                           "approx_size":  false,
                                                                           "size_format":  "ud",
                                                                           "total_units":  null,
                                                                           "unit_selector":  true,
                                                                           "bunch_selector":  false,
                                                                           "drained_weight":  null,
                                                                           "selling_method":  0,
                                                                           "tax_percentage":  "21.000",
                                                                           "price_decreased":  false,
                                                                           "reference_price":  "0.016",
                                                                           "min_bunch_amount":  1.0,
                                                                           "reference_format":  "ud",
                                                                           "previous_unit_price":  null,
                                                                           "increment_bunch_amount":  1.0
                                                                       },
                                                "unavailable_weekdays":  [

                                                                         ],
                                                "is_new_arrival":  false
                                            }
                                        ]
                       },
                       {
                           "id":  759,
                           "name":  "Pañuelos",
                           "order":  374,
                           "layout":  2,
                           "published":  true,
                           "is_extended":  false,
                           "image":  null,
                           "subtitle":  null,
                           "products":  [
                                            {
                                                "id":  "47609",
                                                "slug":  "panuelos-papel-extra-suaves-bosque-verde-2-capas-caja",
                                                "limit":  999,
                                                "badges":  {
                                                               "is_water":  false,
                                                               "requires_age_check":  false
                                                           },
                                                "status":  null,
                                                "packaging":  "Caja",
                                                "published":  true,
                                                "share_url":  "https://tienda.mercadona.es/product/47609/panuelos-papel-extra-suaves-bosque-verde-2-capas-caja",
                                                "thumbnail":  "https://prod-mercadona.imgix.net/images/ee570e175d6894f08bb89c0c35c2e6ee.jpg?fit=crop\u0026h=300\u0026w=300",
                                                "categories":  [
                                                                   {
                                                                       "id":  26,
                                                                       "name":  "Limpieza y hogar",
                                                                       "level":  0,
                                                                       "order":  374
                                                                   }
                                                               ],
                                                "display_name":  "Pañuelos de papel Extra Suaves Bosque Verde",
                                                "unavailable_from":  null,
                                                "price_instructions":  {
                                                                           "iva":  null,
                                                                           "is_new":  false,
                                                                           "is_pack":  false,
                                                                           "pack_size":  null,
                                                                           "unit_name":  null,
                                                                           "unit_size":  200.0,
                                                                           "bulk_price":  "0.01",
                                                                           "unit_price":  "1.30",
                                                                           "approx_size":  false,
                                                                           "size_format":  "ud",
                                                                           "total_units":  null,
                                                                           "unit_selector":  true,
                                                                           "bunch_selector":  false,
                                                                           "drained_weight":  null,
                                                                           "selling_method":  0,
                                                                           "tax_percentage":  "21.000",
                                                                           "price_decreased":  false,
                                                                           "reference_price":  "0.007",
                                                                           "min_bunch_amount":  1.0,
                                                                           "reference_format":  "ud",
                                                                           "previous_unit_price":  null,
                                                                           "increment_bunch_amount":  1.0
                                                                       },
                                                "unavailable_weekdays":  [

                                                                         ],
                                                "is_new_arrival":  false
                                            },
                                            {
                                                "id":  "46703",
                                                "slug":  "panuelos-papel-aloe-vera-bosque-verde-4-capas-paquete",
                                                "limit":  999,
                                                "badges":  {
                                                               "is_water":  false,
                                                               "requires_age_check":  false
                                                           },
                                                "status":  null,
                                                "packaging":  "Paquete",
                                                "published":  true,
                                                "share_url":  "https://tienda.mercadona.es/product/46703/panuelos-papel-aloe-vera-bosque-verde-4-capas-paquete",
                                                "thumbnail":  "https://prod-mercadona.imgix.net/images/7511317815798a118d92064761a95d4b.jpg?fit=crop\u0026h=300\u0026w=300",
                                                "categories":  [
                                                                   {
                                                                       "id":  26,
                                                                       "name":  "Limpieza y hogar",
                                                                       "level":  0,
                                                                       "order":  374
                                                                   }
                                                               ],
                                                "display_name":  "Pañuelos de papel Aloe Vera Bosque Verde",
                                                "unavailable_from":  null,
                                                "price_instructions":  {
                                                                           "iva":  21,
                                                                           "is_new":  false,
                                                                           "is_pack":  false,
                                                                           "pack_size":  null,
                                                                           "unit_name":  null,
                                                                           "unit_size":  10.0,
                                                                           "bulk_price":  "0.02",
                                                                           "unit_price":  "1.60",
                                                                           "approx_size":  false,
                                                                           "size_format":  "ud",
                                                                           "total_units":  null,
                                                                           "unit_selector":  true,
                                                                           "bunch_selector":  false,
                                                                           "drained_weight":  null,
                                                                           "selling_method":  0,
                                                                           "tax_percentage":  "21.000",
                                                                           "price_decreased":  false,
                                                                           "reference_price":  "0.016",
                                                                           "min_bunch_amount":  1.0,
                                                                           "reference_format":  "ud",
                                                                           "previous_unit_price":  null,
                                                                           "increment_bunch_amount":  1.0
                                                                       },
                                                "unavailable_weekdays":  [

                                                                         ],
                                                "is_new_arrival":  false
                                            },
                                            {
                                                "id":  "47620",
                                                "slug":  "panuelos-papel-extra-suaves-bosque-verde-4-capas-paquete",
                                                "limit":  999,
                                                "badges":  {
                                                               "is_water":  false,
                                                               "requires_age_check":  false
                                                           },
                                                "status":  null,
                                                "packaging":  "Paquete",
                                                "published":  true,
                                                "share_url":  "https://tienda.mercadona.es/product/47620/panuelos-papel-extra-suaves-bosque-verde-4-capas-paquete",
                                                "thumbnail":  "https://prod-mercadona.imgix.net/images/b001c95167feeae760dbd0449be877e8.jpg?fit=crop\u0026h=300\u0026w=300",
                                                "categories":  [
                                                                   {
                                                                       "id":  26,
                                                                       "name":  "Limpieza y hogar",
                                                                       "level":  0,
                                                                       "order":  374
                                                                   }
                                                               ],
                                                "display_name":  "Pañuelos de papel Extra Suaves Bosque Verde",
                                                "unavailable_from":  null,
                                                "price_instructions":  {
                                                                           "iva":  null,
                                                                           "is_new":  false,
                                                                           "is_pack":  false,
                                                                           "pack_size":  null,
                                                                           "unit_name":  null,
                                                                           "unit_size":  10.0,
                                                                           "bulk_price":  "0.01",
                                                                           "unit_price":  "1.10",
                                                                           "approx_size":  false,
                                                                           "size_format":  "ud",
                                                                           "total_units":  null,
                                                                           "unit_selector":  true,
                                                                           "bunch_selector":  false,
                                                                           "drained_weight":  null,
                                                                           "selling_method":  0,
                                                                           "tax_percentage":  "21.000",
                                                                           "price_decreased":  false,
                                                                           "reference_price":  "0.011",
                                                                           "min_bunch_amount":  1.0,
                                                                           "reference_format":  "ud",
                                                                           "previous_unit_price":  null,
                                                                           "increment_bunch_amount":  1.0
                                                                       },
                                                "unavailable_weekdays":  [

                                                                         ],
                                                "is_new_arrival":  false
                                            },
                                            {
                                                "id":  "47618",
                                                "slug":  "panuelos-papel-mentol-bosque-verde-4-capas-paquete",
                                                "limit":  999,
                                                "badges":  {
                                                               "is_water":  false,
                                                               "requires_age_check":  false
                                                           },
                                                "status":  null,
                                                "packaging":  "Paquete",
                                                "published":  true,
                                                "share_url":  "https://tienda.mercadona.es/product/47618/panuelos-papel-mentol-bosque-verde-4-capas-paquete",
                                                "thumbnail":  "https://prod-mercadona.imgix.net/images/a9d46a080d602b04ce55132552ad4875.jpg?fit=crop\u0026h=300\u0026w=300",
                                                "categories":  [
                                                                   {
                                                                       "id":  26,
                                                                       "name":  "Limpieza y hogar",
                                                                       "level":  0,
                                                                       "order":  374
                                                                   }
                                                               ],
                                                "display_name":  "Pañuelos de papel Mentol Bosque Verde",
                                                "unavailable_from":  null,
                                                "price_instructions":  {
                                                                           "iva":  21,
                                                                           "is_new":  false,
                                                                           "is_pack":  false,
                                                                           "pack_size":  null,
                                                                           "unit_name":  null,
                                                                           "unit_size":  10.0,
                                                                           "bulk_price":  "0.02",
                                                                           "unit_price":  "1.80",
                                                                           "approx_size":  false,
                                                                           "size_format":  "ud",
                                                                           "total_units":  null,
                                                                           "unit_selector":  true,
                                                                           "bunch_selector":  false,
                                                                           "drained_weight":  null,
                                                                           "selling_method":  0,
                                                                           "tax_percentage":  "21.000",
                                                                           "price_decreased":  false,
                                                                           "reference_price":  "0.018",
                                                                           "min_bunch_amount":  1.0,
                                                                           "reference_format":  "ud",
                                                                           "previous_unit_price":  null,
                                                                           "increment_bunch_amount":  1.0
                                                                       },
                                                "unavailable_weekdays":  [

                                                                         ],
                                                "is_new_arrival":  false
                                            }
                                        ]
                       },
                       {
                           "id":  757,
                           "name":  "Toallitas",
                           "order":  374,
                           "layout":  2,
                           "published":  true,
                           "is_extended":  false,
                           "image":  null,
                           "subtitle":  null,
                           "products":  [
                                            {
                                                "id":  "47828",
                                                "slug":  "toallitas-dermo-higiene-corporal-deliplus-tamano-gigantes-paquete",
                                                "limit":  999,
                                                "badges":  {
                                                               "is_water":  false,
                                                               "requires_age_check":  false
                                                           },
                                                "status":  null,
                                                "packaging":  "Paquete",
                                                "published":  true,
                                                "share_url":  "https://tienda.mercadona.es/product/47828/toallitas-dermo-higiene-corporal-deliplus-tamano-gigantes-paquete",
                                                "thumbnail":  "https://prod-mercadona.imgix.net/images/fc04ecfb53badda995548b003b341c69.jpg?fit=crop\u0026h=300\u0026w=300",
                                                "categories":  [
                                                                   {
                                                                       "id":  26,
                                                                       "name":  "Limpieza y hogar",
                                                                       "level":  0,
                                                                       "order":  374
                                                                   }
                                                               ],
                                                "display_name":  "Toallitas Dermo higiene corporal Deliplus tamaño gigantes",
                                                "unavailable_from":  null,
                                                "price_instructions":  {
                                                                           "iva":  null,
                                                                           "is_new":  false,
                                                                           "is_pack":  false,
                                                                           "pack_size":  null,
                                                                           "unit_name":  null,
                                                                           "unit_size":  60.0,
                                                                           "bulk_price":  "0.07",
                                                                           "unit_price":  "4.00",
                                                                           "approx_size":  false,
                                                                           "size_format":  "ud",
                                                                           "total_units":  null,
                                                                           "unit_selector":  true,
                                                                           "bunch_selector":  false,
                                                                           "drained_weight":  null,
                                                                           "selling_method":  0,
                                                                           "tax_percentage":  "21.000",
                                                                           "price_decreased":  false,
                                                                           "reference_price":  "0.067",
                                                                           "min_bunch_amount":  1.0,
                                                                           "reference_format":  "ud",
                                                                           "previous_unit_price":  null,
                                                                           "increment_bunch_amount":  1.0
                                                                       },
                                                "unavailable_weekdays":  [

                                                                         ],
                                                "is_new_arrival":  false
                                            },
                                            {
                                                "id":  "60560",
                                                "slug":  "toallitas-refrescantes-deliplus-paquete",
                                                "limit":  999,
                                                "badges":  {
                                                               "is_water":  false,
                                                               "requires_age_check":  false
                                                           },
                                                "status":  null,
                                                "packaging":  "Paquete",
                                                "published":  true,
                                                "share_url":  "https://tienda.mercadona.es/product/60560/toallitas-refrescantes-deliplus-paquete",
                                                "thumbnail":  "https://prod-mercadona.imgix.net/images/6a41b4a39861787c46212837d5068648.jpg?fit=crop\u0026h=300\u0026w=300",
                                                "categories":  [
                                                                   {
                                                                       "id":  26,
                                                                       "name":  "Limpieza y hogar",
                                                                       "level":  0,
                                                                       "order":  374
                                                                   }
                                                               ],
                                                "display_name":  "Toallitas refrescantes Deliplus",
                                                "unavailable_from":  null,
                                                "price_instructions":  {
                                                                           "iva":  21,
                                                                           "is_new":  false,
                                                                           "is_pack":  false,
                                                                           "pack_size":  null,
                                                                           "unit_name":  null,
                                                                           "unit_size":  15.0,
                                                                           "bulk_price":  "0.06",
                                                                           "unit_price":  "0.90",
                                                                           "approx_size":  false,
                                                                           "size_format":  "ud",
                                                                           "total_units":  null,
                                                                           "unit_selector":  true,
                                                                           "bunch_selector":  false,
                                                                           "drained_weight":  null,
                                                                           "selling_method":  0,
                                                                           "tax_percentage":  "21.000",
                                                                           "price_decreased":  false,
                                                                           "reference_price":  "0.060",
                                                                           "min_bunch_amount":  1.0,
                                                                           "reference_format":  "ud",
                                                                           "previous_unit_price":  null,
                                                                           "increment_bunch_amount":  1.0
                                                                       },
                                                "unavailable_weekdays":  [

                                                                         ],
                                                "is_new_arrival":  false
                                            },
                                            {
                                                "id":  "60561",
                                                "slug":  "toallitas-refrescantes-deliplus-monodosis-caja",
                                                "limit":  999,
                                                "badges":  {
                                                               "is_water":  false,
                                                               "requires_age_check":  false
                                                           },
                                                "status":  null,
                                                "packaging":  "Caja",
                                                "published":  true,
                                                "share_url":  "https://tienda.mercadona.es/product/60561/toallitas-refrescantes-deliplus-monodosis-caja",
                                                "thumbnail":  "https://prod-mercadona.imgix.net/images/f48b7b31c5afd53bd5cac9a02eaa06be.jpg?fit=crop\u0026h=300\u0026w=300",
                                                "categories":  [
                                                                   {
                                                                       "id":  26,
                                                                       "name":  "Limpieza y hogar",
                                                                       "level":  0,
                                                                       "order":  374
                                                                   }
                                                               ],
                                                "display_name":  "Toallitas refrescantes Deliplus monodosis",
                                                "unavailable_from":  null,
                                                "price_instructions":  {
                                                                           "iva":  21,
                                                                           "is_new":  false,
                                                                           "is_pack":  false,
                                                                           "pack_size":  null,
                                                                           "unit_name":  "sobres",
                                                                           "unit_size":  1.0,
                                                                           "bulk_price":  "0.10",
                                                                           "unit_price":  "1.00",
                                                                           "approx_size":  false,
                                                                           "size_format":  "ud",
                                                                           "total_units":  10,
                                                                           "unit_selector":  true,
                                                                           "bunch_selector":  false,
                                                                           "drained_weight":  null,
                                                                           "selling_method":  0,
                                                                           "tax_percentage":  "21.000",
                                                                           "price_decreased":  false,
                                                                           "reference_price":  "0.100",
                                                                           "min_bunch_amount":  1.0,
                                                                           "reference_format":  "ud",
                                                                           "previous_unit_price":  null,
                                                                           "increment_bunch_amount":  1.0
                                                                       },
                                                "unavailable_weekdays":  [

                                                                         ],
                                                "is_new_arrival":  false
                                            }
                                        ]
                       }
                   ],
    "next_category":  {
                          "id":  239,
                          "name":  "Pilas y bolsas de basura"
                      }
}
